{
	"format_version": "1.12.0",
	"minecraft:geometry": [
		{
			"description": {
				"identifier": "geometry.unknown",
				"texture_width": 128,
				"texture_height": 128,
				"visible_bounds_width": 5,
				"visible_bounds_height": 3.5,
				"visible_bounds_offset": [0, 1.25, 0]
			},
			"bones": [
				{
					"name": "entity",
					"pivot": [0, 0, 0]
				},
				{
					"name": "leg",
					"parent": "entity",
					"pivot": [2.7775, 11.60905, 0.04098],
					"rotation": [25.74131, -21.14635, 0.17007],
					"cubes": [
						{
							"origin": [2.78625, 8.93222, -7.46948],
							"size": [5.5, 5.5, 9.9],
							"pivot": [5.75516, 6.69583, -6.92859],
							"rotation": [0, 0.11792, 0],
							"uv": {
								"north": {"uv": [16, 63], "uv_size": [5, 5]},
								"east": {"uv": [7, 63], "uv_size": [9, 5]},
								"south": {"uv": [30, 63], "uv_size": [5, 5]},
								"west": {"uv": [21, 63], "uv_size": [9, 5]},
								"up": {"uv": [16, 54], "uv_size": [5, 9]},
								"down": {"uv": [21, 63], "uv_size": [5, -9]}
							}
						}
					]
				},
				{
					"name": "foreleg",
					"parent": "leg",
					"pivot": [5.75516, 8.89583, -0.87859],
					"rotation": [-25, 0, 0],
					"cubes": [
						{
							"origin": [2.78725, 3.43322, -5.26848],
							"size": [5.498, 5.498, 4.398],
							"inflate": -0.01,
							"pivot": [5.75516, 6.69583, -6.92859],
							"rotation": [0, 0.11792, 0],
							"uv": {
								"north": {"uv": [10, 73], "uv_size": [5, 5]},
								"east": {"uv": [6, 73], "uv_size": [4, 5]},
								"south": {"uv": [19, 73], "uv_size": [5, 5]},
								"west": {"uv": [15, 73], "uv_size": [4, 5]},
								"up": {"uv": [10, 69], "uv_size": [5, 4]},
								"down": {"uv": [15, 73], "uv_size": [5, -4]}
							}
						}
					]
				},
				{
					"name": "feet",
					"parent": "foreleg",
					"pivot": [5.75516, 3.39583, -3.07859],
					"cubes": [
						{
							"origin": [5.60909, 0.13522, -13.15256],
							"size": [2.198, 3.298, 3.298],
							"inflate": -0.01,
							"pivot": [5.75516, 6.69583, -6.92859],
							"rotation": [0, -19.88108, 0],
							"uv": {
								"north": {"uv": [113, 83], "uv_size": [2, 3]},
								"east": {"uv": [110, 83], "uv_size": [3, 3]},
								"south": {"uv": [118, 83], "uv_size": [2, 3]},
								"west": {"uv": [115, 83], "uv_size": [3, 3]},
								"up": {"uv": [113, 80], "uv_size": [2, 3]},
								"down": {"uv": [115, 83], "uv_size": [2, -3]}
							}
						},
						{
							"origin": [4.43625, 0.13222, -12.96948],
							"size": [2.2, 3.3, 3.3],
							"pivot": [5.75516, 6.69583, -6.92859],
							"rotation": [0, 0.11792, 0],
							"uv": {
								"north": {"uv": [113, 83], "uv_size": [2, 3]},
								"east": {"uv": [110, 83], "uv_size": [3, 3]},
								"south": {"uv": [118, 83], "uv_size": [2, 3]},
								"west": {"uv": [115, 83], "uv_size": [3, 3]},
								"up": {"uv": [113, 80], "uv_size": [2, 3]},
								"down": {"uv": [115, 83], "uv_size": [2, -3]}
							}
						},
						{
							"origin": [3.38766, 0.13102, -13.28652],
							"size": [2.198, 3.298, 3.298],
							"inflate": -0.01,
							"pivot": [5.75516, 6.69583, -6.92859],
							"rotation": [0, 22.61678, 0],
							"uv": {
								"north": {"uv": [113, 83], "uv_size": [2, 3]},
								"east": {"uv": [110, 83], "uv_size": [3, 3]},
								"south": {"uv": [118, 83], "uv_size": [2, 3]},
								"west": {"uv": [115, 83], "uv_size": [3, 3]},
								"up": {"uv": [113, 80], "uv_size": [2, 3]},
								"down": {"uv": [115, 83], "uv_size": [2, -3]}
							}
						},
						{
							"origin": [2.23625, 0.13222, -9.66948],
							"size": [6.6, 3.3, 9.9],
							"pivot": [5.75516, 6.69583, -6.92859],
							"rotation": [0, 0.11792, 0],
							"uv": {
								"north": {"uv": [31, 10], "uv_size": [6, 3]},
								"east": {"uv": [22, 10], "uv_size": [9, 3]},
								"south": {"uv": [46, 10], "uv_size": [6, 3]},
								"west": {"uv": [37, 10], "uv_size": [9, 3]},
								"up": {"uv": [31, 1], "uv_size": [6, 9]},
								"down": {"uv": [37, 10], "uv_size": [6, -9]}
							}
						}
					]
				},
				{
					"name": "leg2",
					"parent": "entity",
					"pivot": [-2.7775, 11.60905, 0.04098],
					"rotation": [25.74131, 21.14635, -0.17007],
					"cubes": [
						{
							"origin": [-8.28625, 8.93222, -7.46948],
							"size": [5.5, 5.5, 9.9],
							"pivot": [-5.75516, 6.69583, -6.92859],
							"rotation": [0, -0.11792, 0],
							"uv": {
								"north": {"uv": [21, 63], "uv_size": [-5, 5]},
								"east": {"uv": [30, 63], "uv_size": [-9, 5]},
								"south": {"uv": [35, 63], "uv_size": [-5, 5]},
								"west": {"uv": [16, 63], "uv_size": [-9, 5]},
								"up": {"uv": [21, 54], "uv_size": [-5, 9]},
								"down": {"uv": [26, 63], "uv_size": [-5, -9]}
							}
						}
					]
				},
				{
					"name": "foreleg2",
					"parent": "leg2",
					"pivot": [-5.75516, 8.89583, -0.87859],
					"rotation": [-25, 0, 0],
					"cubes": [
						{
							"origin": [-8.28525, 3.43322, -5.26848],
							"size": [5.498, 5.498, 4.398],
							"inflate": -0.01,
							"pivot": [-5.75516, 6.69583, -6.92859],
							"rotation": [0, -0.11792, 0],
							"uv": {
								"north": {"uv": [15, 73], "uv_size": [-5, 5]},
								"east": {"uv": [19, 73], "uv_size": [-4, 5]},
								"south": {"uv": [24, 73], "uv_size": [-5, 5]},
								"west": {"uv": [10, 73], "uv_size": [-4, 5]},
								"up": {"uv": [15, 69], "uv_size": [-5, 4]},
								"down": {"uv": [20, 73], "uv_size": [-5, -4]}
							}
						}
					]
				},
				{
					"name": "feet2",
					"parent": "foreleg2",
					"pivot": [-5.75516, 3.39583, -3.07859],
					"cubes": [
						{
							"origin": [-7.80709, 0.13522, -13.15256],
							"size": [2.198, 3.298, 3.298],
							"inflate": -0.01,
							"pivot": [-5.75516, 6.69583, -6.92859],
							"rotation": [0, 19.88108, 0],
							"uv": {
								"north": {"uv": [115, 83], "uv_size": [-2, 3]},
								"east": {"uv": [118, 83], "uv_size": [-3, 3]},
								"south": {"uv": [120, 83], "uv_size": [-2, 3]},
								"west": {"uv": [113, 83], "uv_size": [-3, 3]},
								"up": {"uv": [115, 80], "uv_size": [-2, 3]},
								"down": {"uv": [117, 83], "uv_size": [-2, -3]}
							}
						},
						{
							"origin": [-6.63625, 0.13222, -12.96948],
							"size": [2.2, 3.3, 3.3],
							"pivot": [-5.75516, 6.69583, -6.92859],
							"rotation": [0, -0.11792, 0],
							"uv": {
								"north": {"uv": [115, 83], "uv_size": [-2, 3]},
								"east": {"uv": [118, 83], "uv_size": [-3, 3]},
								"south": {"uv": [120, 83], "uv_size": [-2, 3]},
								"west": {"uv": [113, 83], "uv_size": [-3, 3]},
								"up": {"uv": [115, 80], "uv_size": [-2, 3]},
								"down": {"uv": [117, 83], "uv_size": [-2, -3]}
							}
						},
						{
							"origin": [-5.58566, 0.13102, -13.28652],
							"size": [2.198, 3.298, 3.298],
							"inflate": -0.01,
							"pivot": [-5.75516, 6.69583, -6.92859],
							"rotation": [0, -22.61678, 0],
							"uv": {
								"north": {"uv": [115, 83], "uv_size": [-2, 3]},
								"east": {"uv": [118, 83], "uv_size": [-3, 3]},
								"south": {"uv": [120, 83], "uv_size": [-2, 3]},
								"west": {"uv": [113, 83], "uv_size": [-3, 3]},
								"up": {"uv": [115, 80], "uv_size": [-2, 3]},
								"down": {"uv": [117, 83], "uv_size": [-2, -3]}
							}
						},
						{
							"origin": [-8.83625, 0.13222, -9.66948],
							"size": [6.6, 3.3, 9.9],
							"pivot": [-5.75516, 6.69583, -6.92859],
							"rotation": [0, -0.11792, 0],
							"uv": {
								"north": {"uv": [37, 10], "uv_size": [-6, 3]},
								"east": {"uv": [46, 10], "uv_size": [-9, 3]},
								"south": {"uv": [52, 10], "uv_size": [-6, 3]},
								"west": {"uv": [31, 10], "uv_size": [-9, 3]},
								"up": {"uv": [37, 1], "uv_size": [-6, 9]},
								"down": {"uv": [43, 10], "uv_size": [-6, -9]}
							}
						}
					]
				},
				{
					"name": "body",
					"parent": "entity",
					"pivot": [0, 12.54, -1.1],
					"cubes": [
						{
							"origin": [-3.85, 24.28655, -3.47902],
							"size": [7.7, 7.7, 11],
							"pivot": [0, 26.26655, -6.88902],
							"rotation": [-70, 0, 0],
							"uv": {
								"north": {"uv": [59, 64], "uv_size": [7, 7]},
								"east": {"uv": [49, 64], "uv_size": [10, 7]},
								"south": {"uv": [76, 64], "uv_size": [7, 7]},
								"west": {"uv": [66, 64], "uv_size": [10, 7]},
								"up": {"uv": [59, 54], "uv_size": [7, 10]},
								"down": {"uv": [66, 64], "uv_size": [7, -10]}
							}
						}
					]
				},
				{
					"name": "arm",
					"parent": "body",
					"pivot": [4.4, 21.63445, -3.21306],
					"rotation": [-4.94738, 22.83078, -45.61755],
					"cubes": [
						{
							"origin": [3.85, 25.38655, -3.47902],
							"size": [3.3, 5.5, 4.4],
							"pivot": [0, 26.26655, -6.88902],
							"rotation": [-70, 0, 0],
							"uv": {
								"north": {"uv": [44, 57], "uv_size": [3, 5]},
								"east": {"uv": [40, 57], "uv_size": [4, 5]},
								"south": {"uv": [51, 57], "uv_size": [3, 5]},
								"west": {"uv": [47, 57], "uv_size": [4, 5]},
								"up": {"uv": [44, 53], "uv_size": [3, 4]},
								"down": {"uv": [47, 57], "uv_size": [3, -4]}
							}
						},
						{
							"origin": [4.4, 26.48655, 0.92098],
							"size": [2.2, 3.3, 5.5],
							"pivot": [0, 26.26655, -6.88902],
							"rotation": [-70, 0, 0],
							"uv": {
								"north": {"uv": [118, 103], "uv_size": [2, 3]},
								"east": {"uv": [113, 103], "uv_size": [5, 3]},
								"south": {"uv": [125, 103], "uv_size": [2, 3]},
								"west": {"uv": [120, 103], "uv_size": [5, 3]},
								"up": {"uv": [118, 98], "uv_size": [2, 5]},
								"down": {"uv": [120, 103], "uv_size": [2, -5]}
							}
						}
					]
				},
				{
					"name": "forearm",
					"parent": "arm",
					"pivot": [5.5, 13.7598, -2.47817],
					"rotation": [30, 0, 0],
					"cubes": [
						{
							"origin": [3.85, 16.58655, 4.22098],
							"size": [3.3, 12.1, 5.5],
							"pivot": [0, 25.16655, -6.88902],
							"rotation": [-70, 0, 0],
							"uv": {
								"north": {"uv": [101, 103], "uv_size": [3, 11]},
								"east": {"uv": [96, 103], "uv_size": [5, 11]},
								"south": {"uv": [109, 103], "uv_size": [3, 11]},
								"west": {"uv": [104, 103], "uv_size": [5, 11]},
								"up": {"uv": [101, 98], "uv_size": [3, 5]},
								"down": {"uv": [104, 103], "uv_size": [3, -5]}
							}
						},
						{
							"origin": [6.05, 5.61602, -4.36804],
							"size": [0, 15.4, 7.7],
							"inflate": 0.01,
							"pivot": [6.05, 10.0126, 0.02765],
							"rotation": [-130, 0, 0],
							"uv": {
								"north": {"uv": [87, 104], "uv_size": [0, 14]},
								"east": {"uv": [80, 104], "uv_size": [7, 14]},
								"south": {"uv": [94, 104], "uv_size": [0, 14]},
								"west": {"uv": [87, 104], "uv_size": [7, 14]},
								"up": {"uv": [84, 97], "uv_size": [0, 7]},
								"down": {"uv": [84, 104], "uv_size": [0, -7]}
							}
						},
						{
							"origin": [3.85, 12.18655, 4.22098],
							"size": [2.2, 4.4, 1.1],
							"pivot": [0, 25.16655, -6.88902],
							"rotation": [-70, 0, 0],
							"uv": {
								"north": {"uv": [88, 99], "uv_size": [2, 4]},
								"east": {"uv": [87, 99], "uv_size": [1, 4]},
								"south": {"uv": [91, 99], "uv_size": [2, 4]},
								"west": {"uv": [90, 99], "uv_size": [1, 4]},
								"up": {"uv": [88, 98], "uv_size": [2, 1]},
								"down": {"uv": [90, 99], "uv_size": [2, -1]}
							}
						},
						{
							"origin": [3.85, 12.18655, 8.62098],
							"size": [2.2, 4.4, 1.1],
							"pivot": [0, 25.16655, -6.88902],
							"rotation": [-70, 0, 0],
							"uv": {
								"north": {"uv": [88, 99], "uv_size": [2, 4]},
								"east": {"uv": [87, 99], "uv_size": [1, 4]},
								"south": {"uv": [91, 99], "uv_size": [2, 4]},
								"west": {"uv": [90, 99], "uv_size": [1, 4]},
								"up": {"uv": [88, 98], "uv_size": [2, 1]},
								"down": {"uv": [90, 99], "uv_size": [2, -1]}
							}
						},
						{
							"origin": [3.85, 12.18655, 6.42098],
							"size": [2.2, 4.4, 1.1],
							"pivot": [0, 25.16655, -6.88902],
							"rotation": [-70, 0, 0],
							"uv": {
								"north": {"uv": [88, 99], "uv_size": [2, 4]},
								"east": {"uv": [87, 99], "uv_size": [1, 4]},
								"south": {"uv": [91, 99], "uv_size": [2, 4]},
								"west": {"uv": [90, 99], "uv_size": [1, 4]},
								"up": {"uv": [88, 98], "uv_size": [2, 1]},
								"down": {"uv": [90, 99], "uv_size": [2, -1]}
							}
						}
					]
				},
				{
					"name": "arm2",
					"parent": "body",
					"pivot": [-4.4, 21.63445, -3.21306],
					"rotation": [-4.94738, -22.83078, 45.61755],
					"cubes": [
						{
							"origin": [-7.15, 25.38655, -3.47902],
							"size": [3.3, 5.5, 4.4],
							"pivot": [0, 26.26655, -6.88902],
							"rotation": [-70, 0, 0],
							"uv": {
								"north": {"uv": [47, 57], "uv_size": [-3, 5]},
								"east": {"uv": [51, 57], "uv_size": [-4, 5]},
								"south": {"uv": [54, 57], "uv_size": [-3, 5]},
								"west": {"uv": [44, 57], "uv_size": [-4, 5]},
								"up": {"uv": [47, 53], "uv_size": [-3, 4]},
								"down": {"uv": [50, 57], "uv_size": [-3, -4]}
							}
						},
						{
							"origin": [-6.6, 26.48655, 0.92098],
							"size": [2.2, 3.3, 5.5],
							"pivot": [0, 26.26655, -6.88902],
							"rotation": [-70, 0, 0],
							"uv": {
								"north": {"uv": [120, 103], "uv_size": [-2, 3]},
								"east": {"uv": [125, 103], "uv_size": [-5, 3]},
								"south": {"uv": [127, 103], "uv_size": [-2, 3]},
								"west": {"uv": [118, 103], "uv_size": [-5, 3]},
								"up": {"uv": [120, 98], "uv_size": [-2, 5]},
								"down": {"uv": [122, 103], "uv_size": [-2, -5]}
							}
						}
					]
				},
				{
					"name": "forearm2",
					"parent": "arm2",
					"pivot": [-5.5, 13.7598, -2.47817],
					"rotation": [30, 0, 0],
					"cubes": [
						{
							"origin": [-7.15, 16.58655, 4.22098],
							"size": [3.3, 12.1, 5.5],
							"pivot": [0, 25.16655, -6.88902],
							"rotation": [-70, 0, 0],
							"uv": {
								"north": {"uv": [104, 103], "uv_size": [-3, 11]},
								"east": {"uv": [109, 103], "uv_size": [-5, 11]},
								"south": {"uv": [112, 103], "uv_size": [-3, 11]},
								"west": {"uv": [101, 103], "uv_size": [-5, 11]},
								"up": {"uv": [104, 98], "uv_size": [-3, 5]},
								"down": {"uv": [107, 103], "uv_size": [-3, -5]}
							}
						},
						{
							"origin": [-6.05, 5.61602, -4.36804],
							"size": [0, 15.4, 7.7],
							"inflate": 0.01,
							"pivot": [-6.05, 10.0126, 0.02765],
							"rotation": [-130, 0, 0],
							"uv": {
								"north": {"uv": [87, 104], "uv_size": [0, 14]},
								"east": {"uv": [94, 104], "uv_size": [-7, 14]},
								"south": {"uv": [94, 104], "uv_size": [0, 14]},
								"west": {"uv": [87, 104], "uv_size": [-7, 14]},
								"up": {"uv": [84, 97], "uv_size": [0, 7]},
								"down": {"uv": [84, 104], "uv_size": [0, -7]}
							}
						},
						{
							"origin": [-6.05, 12.18655, 4.22098],
							"size": [2.2, 4.4, 1.1],
							"pivot": [0, 25.16655, -6.88902],
							"rotation": [-70, 0, 0],
							"uv": {
								"north": {"uv": [90, 99], "uv_size": [-2, 4]},
								"east": {"uv": [91, 99], "uv_size": [-1, 4]},
								"south": {"uv": [93, 99], "uv_size": [-2, 4]},
								"west": {"uv": [88, 99], "uv_size": [-1, 4]},
								"up": {"uv": [90, 98], "uv_size": [-2, 1]},
								"down": {"uv": [92, 99], "uv_size": [-2, -1]}
							}
						},
						{
							"origin": [-6.05, 12.18655, 8.62098],
							"size": [2.2, 4.4, 1.1],
							"pivot": [0, 25.16655, -6.88902],
							"rotation": [-70, 0, 0],
							"uv": {
								"north": {"uv": [90, 99], "uv_size": [-2, 4]},
								"east": {"uv": [91, 99], "uv_size": [-1, 4]},
								"south": {"uv": [93, 99], "uv_size": [-2, 4]},
								"west": {"uv": [88, 99], "uv_size": [-1, 4]},
								"up": {"uv": [90, 98], "uv_size": [-2, 1]},
								"down": {"uv": [92, 99], "uv_size": [-2, -1]}
							}
						},
						{
							"origin": [-6.05, 12.18655, 6.42098],
							"size": [2.2, 4.4, 1.1],
							"pivot": [0, 25.16655, -6.88902],
							"rotation": [-70, 0, 0],
							"uv": {
								"north": {"uv": [90, 99], "uv_size": [-2, 4]},
								"east": {"uv": [91, 99], "uv_size": [-1, 4]},
								"south": {"uv": [93, 99], "uv_size": [-2, 4]},
								"west": {"uv": [88, 99], "uv_size": [-1, 4]},
								"up": {"uv": [90, 98], "uv_size": [-2, 1]},
								"down": {"uv": [92, 99], "uv_size": [-2, -1]}
							}
						}
					]
				},
				{
					"name": "tail",
					"parent": "body",
					"pivot": [0, 12.04905, -3.80902],
					"rotation": [40, 0, 0],
					"cubes": [
						{
							"origin": [-3.849, 26.37755, 8.97948],
							"size": [7.698, 6.598, 8.798],
							"inflate": -0.01,
							"pivot": [0, 28.35655, -7.63152],
							"rotation": [-70, 0, 0],
							"uv": {
								"north": {"uv": [94, 64], "uv_size": [7, 6]},
								"east": {"uv": [86, 64], "uv_size": [8, 6]},
								"south": {"uv": [109, 64], "uv_size": [7, 6]},
								"west": {"uv": [101, 64], "uv_size": [8, 6]},
								"up": {"uv": [94, 56], "uv_size": [7, 8]},
								"down": {"uv": [101, 64], "uv_size": [7, -8]}
							}
						},
						{
							"origin": [-2.199, -0.97567, 6.59391],
							"size": [4.398, 5.498, 10.998],
							"inflate": -0.01,
							"pivot": [0, -0.95845, 6.58598],
							"rotation": [10.75, 0, 0],
							"uv": {
								"north": {"uv": [29, 90], "uv_size": [4, 5]},
								"east": {"uv": [19, 90], "uv_size": [10, 5]},
								"south": {"uv": [43, 90], "uv_size": [4, 5]},
								"west": {"uv": [33, 90], "uv_size": [10, 5]},
								"up": {"uv": [29, 80], "uv_size": [4, 10]},
								"down": {"uv": [33, 90], "uv_size": [4, -10]}
							}
						},
						{
							"origin": [-2.75, 3.78366, -0.7925],
							"size": [5.5, 5.5, 8.8],
							"pivot": [0, 3.79905, -0.78402],
							"rotation": [-32.75, 0, 0],
							"uv": {
								"north": {"uv": [93, 90], "uv_size": [5, 5]},
								"east": {"uv": [85, 90], "uv_size": [8, 5]},
								"south": {"uv": [106, 90], "uv_size": [5, 5]},
								"west": {"uv": [98, 90], "uv_size": [8, 5]},
								"up": {"uv": [93, 82], "uv_size": [5, 8]},
								"down": {"uv": [98, 90], "uv_size": [5, -8]}
							}
						},
						{
							"origin": [-1.65, 2.05905, 16.36591],
							"size": [3.3, 4.4, 8.8],
							"pivot": [0, 6.46655, 16.37598],
							"rotation": [-25.25, 0, 0],
							"uv": {
								"north": {"uv": [64, 88], "uv_size": [3, 4]},
								"east": {"uv": [56, 88], "uv_size": [8, 4]},
								"south": {"uv": [75, 88], "uv_size": [3, 4]},
								"west": {"uv": [67, 88], "uv_size": [8, 4]},
								"up": {"uv": [64, 80], "uv_size": [3, 8]},
								"down": {"uv": [67, 88], "uv_size": [3, -8]}
							}
						}
					]
				},
				{
					"name": "neck",
					"parent": "body",
					"pivot": [0, 24.97405, -0.37152],
					"cubes": [
						{
							"origin": [-3.298, 22.28105, -12.46952],
							"size": [6.596, 7.696, 10.996],
							"inflate": -0.02,
							"pivot": [0, 26.12905, -6.97152],
							"rotation": [-45, 0, 0],
							"uv": {
								"north": {"uv": [103, 12], "uv_size": [6, 7]},
								"east": {"uv": [93, 12], "uv_size": [10, 7]},
								"south": {"uv": [119, 12], "uv_size": [6, 7]},
								"west": {"uv": [109, 12], "uv_size": [10, 7]},
								"up": {"uv": [103, 2], "uv_size": [6, 10]},
								"down": {"uv": [109, 12], "uv_size": [6, -10]}
							}
						},
						{
							"origin": [-2.75, 29.89655, -11.37152],
							"size": [5.5, 2.2, 9.9],
							"pivot": [0, 26.12905, -6.97152],
							"rotation": [-45, 0, 0],
							"uv": {
								"north": {"uv": [102, 51], "uv_size": [5, 2]},
								"east": {"uv": [93, 51], "uv_size": [9, 2]},
								"south": {"uv": [116, 51], "uv_size": [5, 2]},
								"west": {"uv": [107, 51], "uv_size": [9, 2]},
								"up": {"uv": [102, 42], "uv_size": [5, 9]},
								"down": {"uv": [107, 51], "uv_size": [5, -9]}
							}
						}
					]
				},
				{
					"name": "head_",
					"parent": "neck",
					"pivot": [0, 25.7125, -10.2025],
					"cubes": [
						{
							"origin": [-3.3, 26.8125, -20.1025],
							"size": [6.6, 4.4, 12.1],
							"uv": {
								"north": {"uv": [68, 21], "uv_size": [6, 4]},
								"east": {"uv": [57, 21], "uv_size": [11, 4]},
								"south": {"uv": [85, 21], "uv_size": [6, 4]},
								"west": {"uv": [74, 21], "uv_size": [11, 4]},
								"up": {"uv": [68, 10], "uv_size": [6, 11]},
								"down": {"uv": [74, 21], "uv_size": [6, -11]}
							}
						},
						{
							"origin": [-3.302, 25.7105, -20.0795],
							"size": [6.604, 1.104, 7.704],
							"inflate": 0.02,
							"uv": {
								"north": {"uv": [20, 44], "uv_size": [6, 1]},
								"east": {"uv": [13, 44], "uv_size": [7, 1]},
								"south": {"uv": [33, 44], "uv_size": [6, 1]},
								"west": {"uv": [26, 44], "uv_size": [7, 1]},
								"up": {"uv": [20, 37], "uv_size": [6, 7]},
								"down": {"uv": [26, 44], "uv_size": [6, -7]}
							}
						},
						{
							"origin": [3.3, 25.7125, -8.0025],
							"size": [3.3, 5.5, 0],
							"inflate": 0.01,
							"pivot": [3.3, 28.4625, -8.0025],
							"rotation": [0, -27.5, 0],
							"uv": {
								"north": {"uv": [61, 11], "uv_size": [-3, 5]},
								"east": {"uv": [61, 11], "uv_size": [0, 5]},
								"south": {"uv": [64, 11], "uv_size": [-3, 5]},
								"west": {"uv": [58, 11], "uv_size": [0, 5]},
								"up": {"uv": [61, 11], "uv_size": [-3, 0]},
								"down": {"uv": [64, 11], "uv_size": [-3, 0]}
							}
						},
						{
							"origin": [-6.6, 25.7125, -8.0025],
							"size": [3.3, 5.5, 0],
							"inflate": 0.01,
							"pivot": [-3.3, 28.4625, -8.0025],
							"rotation": [0, 27.5, 0],
							"uv": {
								"north": {"uv": [58, 11], "uv_size": [3, 5]},
								"east": {"uv": [58, 11], "uv_size": [0, 5]},
								"south": {"uv": [61, 11], "uv_size": [3, 5]},
								"west": {"uv": [61, 11], "uv_size": [0, 5]},
								"up": {"uv": [58, 11], "uv_size": [3, 0]},
								"down": {"uv": [61, 11], "uv_size": [3, 0]}
							}
						},
						{
							"origin": [-3.3, 31.2125, -15.7025],
							"size": [6.6, 2.2, 7.7],
							"uv": {
								"north": {"uv": [65, 7], "uv_size": [6, 2]},
								"east": {"uv": [58, 7], "uv_size": [7, 2]},
								"south": {"uv": [78, 7], "uv_size": [6, 2]},
								"west": {"uv": [71, 7], "uv_size": [7, 2]},
								"up": {"uv": [65, 0], "uv_size": [6, 7]},
								"down": {"uv": [71, 7], "uv_size": [6, -7]}
							}
						},
						{
							"origin": [-2.75, 33.4125, -10.2025],
							"size": [5.5, 1.1, 2.2],
							"uv": {
								"north": {"uv": [101, 24], "uv_size": [5, 1]},
								"east": {"uv": [99, 24], "uv_size": [2, 1]},
								"south": {"uv": [108, 24], "uv_size": [5, 1]},
								"west": {"uv": [106, 24], "uv_size": [2, 1]},
								"up": {"uv": [101, 22], "uv_size": [5, 2]},
								"down": {"uv": [106, 24], "uv_size": [5, -2]}
							}
						},
						{
							"origin": [-1.65, 33.4125, -12.4025],
							"size": [3.3, 1.1, 2.2],
							"uv": {
								"north": {"uv": [111, 30], "uv_size": [3, 1]},
								"east": {"uv": [109, 30], "uv_size": [2, 1]},
								"south": {"uv": [116, 30], "uv_size": [3, 1]},
								"west": {"uv": [114, 30], "uv_size": [2, 1]},
								"up": {"uv": [111, 28], "uv_size": [3, 2]},
								"down": {"uv": [114, 30], "uv_size": [3, -2]}
							}
						},
						{
							"origin": [-2.751, 27.9115, -8.0035],
							"size": [5.502, 5.502, 2.202],
							"inflate": 0.01,
							"uv": {
								"north": {"uv": [102, 35], "uv_size": [5, 5]},
								"east": {"uv": [100, 35], "uv_size": [2, 5]},
								"south": {"uv": [109, 35], "uv_size": [5, 5]},
								"west": {"uv": [107, 35], "uv_size": [2, 5]},
								"up": {"uv": [102, 33], "uv_size": [5, 2]},
								"down": {"uv": [107, 35], "uv_size": [5, -2]}
							}
						},
						{
							"origin": [-3.3, 33.4125, -13.5025],
							"size": [2.2, 5.5, 3.3],
							"pivot": [-1.1, 33.4125, -11.8525],
							"rotation": [0, 0, -22.5],
							"uv": {
								"north": {"uv": [84, 15], "uv_size": [2, 5]},
								"east": {"uv": [81, 15], "uv_size": [3, 5]},
								"south": {"uv": [89, 15], "uv_size": [2, 5]},
								"west": {"uv": [86, 15], "uv_size": [3, 5]},
								"up": {"uv": [84, 12], "uv_size": [2, 3]},
								"down": {"uv": [86, 15], "uv_size": [2, -3]}
							}
						},
						{
							"origin": [1.1, 33.4125, -13.5025],
							"size": [2.2, 5.5, 3.3],
							"pivot": [1.1, 33.4125, -11.8525],
							"rotation": [0, 0, 22.5],
							"uv": {
								"north": {"uv": [84, 15], "uv_size": [2, 5]},
								"east": {"uv": [81, 15], "uv_size": [3, 5]},
								"south": {"uv": [89, 15], "uv_size": [2, 5]},
								"west": {"uv": [86, 15], "uv_size": [3, 5]},
								"up": {"uv": [84, 12], "uv_size": [2, 3]},
								"down": {"uv": [86, 15], "uv_size": [2, -3]}
							}
						},
						{
							"origin": [3.3, 32.4225, -12.4025],
							"size": [0, 7.7, 7.7],
							"inflate": 0.01,
							"pivot": [3.3, 32.4225, -9.1025],
							"rotation": [-63.21865, 20.29348, 9.92926],
							"uv": {
								"north": {"uv": [83, 40], "uv_size": [0, 7]},
								"east": {"uv": [76, 40], "uv_size": [7, 7]},
								"south": {"uv": [90, 40], "uv_size": [0, 7]},
								"west": {"uv": [83, 40], "uv_size": [7, 7]},
								"up": {"uv": [92, 33], "uv_size": [0, 7]},
								"down": {"uv": [92, 40], "uv_size": [0, -7]}
							}
						},
						{
							"origin": [-4.4, 24.6125, -8.0025],
							"size": [1.1, 2.2, 0],
							"inflate": 0.01,
							"pivot": [-3.3, 25.7125, -8.0025],
							"rotation": [0, 27.5, 0],
							"uv": {
								"north": {"uv": [58, 27], "uv_size": [1, 2]},
								"east": {"uv": [58, 27], "uv_size": [0, 2]},
								"south": {"uv": [59, 27], "uv_size": [1, 2]},
								"west": {"uv": [59, 27], "uv_size": [0, 2]},
								"up": {"uv": [58, 27], "uv_size": [1, 0]},
								"down": {"uv": [59, 27], "uv_size": [1, 0]}
							}
						},
						{
							"origin": [-3.3, 24.6125, -12.4025],
							"size": [6.6, 2.2, 4.4],
							"uv": {
								"north": {"uv": [55, 47], "uv_size": [6, 2]},
								"east": {"uv": [51, 47], "uv_size": [4, 2]},
								"south": {"uv": [65, 47], "uv_size": [6, 2]},
								"west": {"uv": [61, 47], "uv_size": [4, 2]},
								"up": {"uv": [55, 43], "uv_size": [6, 4]},
								"down": {"uv": [61, 47], "uv_size": [6, -4]}
							}
						},
						{
							"origin": [3.3, 24.6125, -8.0025],
							"size": [1.1, 2.2, 0],
							"inflate": 0.01,
							"pivot": [3.3, 25.7125, -8.0025],
							"rotation": [0, -27.5, 0],
							"uv": {
								"north": {"uv": [58, 27], "uv_size": [1, 2]},
								"east": {"uv": [58, 27], "uv_size": [0, 2]},
								"south": {"uv": [59, 27], "uv_size": [1, 2]},
								"west": {"uv": [59, 27], "uv_size": [0, 2]},
								"up": {"uv": [58, 27], "uv_size": [1, 0]},
								"down": {"uv": [59, 27], "uv_size": [1, 0]}
							}
						},
						{
							"origin": [-3.3, 32.4225, -12.4025],
							"size": [0, 7.7, 7.7],
							"inflate": 0.01,
							"pivot": [-3.3, 32.4225, -9.1025],
							"rotation": [-63.21865, -20.29348, -9.92926],
							"uv": {
								"north": {"uv": [83, 40], "uv_size": [0, 7]},
								"east": {"uv": [76, 40], "uv_size": [7, 7]},
								"south": {"uv": [90, 40], "uv_size": [0, 7]},
								"west": {"uv": [83, 40], "uv_size": [7, 7]},
								"up": {"uv": [92, 33], "uv_size": [0, 7]},
								"down": {"uv": [92, 40], "uv_size": [0, -7]}
							}
						}
					]
				},
				{
					"name": "lower_jaw",
					"parent": "head_",
					"pivot": [0, 26.8125, -12.4025],
					"cubes": [
						{
							"origin": [-3.301, 24.6115, -19.0035],
							"size": [6.602, 2.202, 6.602],
							"inflate": 0.01,
							"uv": {
								"north": {"uv": [68, 37], "uv_size": [6, 2]},
								"east": {"uv": [62, 37], "uv_size": [6, 2]},
								"south": {"uv": [80, 37], "uv_size": [6, 2]},
								"west": {"uv": [74, 37], "uv_size": [6, 2]},
								"up": {"uv": [68, 31], "uv_size": [6, 6]},
								"down": {"uv": [74, 37], "uv_size": [6, -6]}
							}
						}
					]
				}
			]
		}
	]
}