{
	"format_version": "1.12.0",
	"minecraft:geometry": [
		{
			"description": {
				"identifier": "geometry.unknown",
				"texture_width": 128,
				"texture_height": 128,
				"visible_bounds_width": 4,
				"visible_bounds_height": 4.5,
				"visible_bounds_offset": [0, 1.75, 0]
			},
			"bones": [
				{
					"name": "entity",
					"pivot": [0, 0, 0]
				},
				{
					"name": "body",
					"parent": "entity",
					"pivot": [0, 15.60589, 1.51458],
					"cubes": [
						{
							"origin": [-2.5, 32.10589, -1.02999],
							"size": [5, 3, 5],
							"uv": {
								"north": {"uv": [58.66667, 45.33333], "uv_size": [6.66667, 4]},
								"east": {"uv": [52, 45.33333], "uv_size": [6.66667, 4]},
								"south": {"uv": [72, 45.33333], "uv_size": [6.66667, 4]},
								"west": {"uv": [65.33333, 45.33333], "uv_size": [6.66667, 4]},
								"up": {"uv": [58.66667, 38.66667], "uv_size": [6.66667, 6.66667]},
								"down": {"uv": [65.33333, 45.33333], "uv_size": [6.66667, -6.66667]}
							}
						},
						{
							"origin": [-4.5, 25.10589, -2.02999],
							"size": [9, 7, 6],
							"uv": {
								"north": {"uv": [48, 26.66667], "uv_size": [12, 9.33333]},
								"east": {"uv": [40, 26.66667], "uv_size": [8, 9.33333]},
								"south": {"uv": [68, 26.66667], "uv_size": [12, 9.33333]},
								"west": {"uv": [60, 26.66667], "uv_size": [8, 9.33333]},
								"up": {"uv": [48, 18.66667], "uv_size": [12, 8]},
								"down": {"uv": [60, 26.66667], "uv_size": [12, -8]}
							}
						},
						{
							"origin": [2.5, 14.10589, 3.97001],
							"size": [0, 36, 9],
							"inflate": 0.01,
							"pivot": [2.5, 30.10589, 3.97001],
							"rotation": [0, 47.5, 0],
							"uv": {
								"north": {"uv": [116, 22.66667], "uv_size": [0, 48]},
								"east": {"uv": [128, 22.66667], "uv_size": [-12, 48]},
								"south": {"uv": [128, 22.66667], "uv_size": [0, 48]},
								"west": {"uv": [116, 22.66667], "uv_size": [12, 48]},
								"up": {"uv": [112, 24], "uv_size": [0, 4]},
								"down": {"uv": [112, 28], "uv_size": [0, -4]}
							}
						},
						{
							"origin": [-4.1355, 10.10589, 10.05032],
							"size": [0, 36, 9],
							"inflate": 0.01,
							"pivot": [2.5, 30.10589, 3.97001],
							"rotation": [-180, 85, 180],
							"uv": {
								"north": {"uv": [114.66667, 22.66667], "uv_size": [0, 48]},
								"east": {"uv": [12, 0], "uv_size": [-12, 48]},
								"south": {"uv": [114.66667, 22.66667], "uv_size": [0, 48]},
								"west": {"uv": [0, 0], "uv_size": [12, 48]},
								"up": {"uv": [117.33333, 29.33333], "uv_size": [-1.33333, 9.33333]},
								"down": {"uv": [117.33333, 38.66667], "uv_size": [-1.33333, -9.33333]}
							}
						},
						{
							"origin": [-2.5, 14.10589, 3.97001],
							"size": [0, 36, 9],
							"inflate": 0.01,
							"pivot": [-2.5, 30.10589, 3.97001],
							"rotation": [0, -47.5, 0],
							"uv": {
								"north": {"uv": [116, 22.66667], "uv_size": [0, 48]},
								"east": {"uv": [128, 22.66667], "uv_size": [-12, 48]},
								"south": {"uv": [128, 22.66667], "uv_size": [0, 48]},
								"west": {"uv": [116, 22.66667], "uv_size": [12, 48]},
								"up": {"uv": [114.66667, 29.33333], "uv_size": [1.33333, 5.33333]},
								"down": {"uv": [114.66667, 34.66667], "uv_size": [1.33333, -5.33333]}
							}
						},
						{
							"origin": [4.1355, 10.10589, 10.05032],
							"size": [0, 36, 9],
							"inflate": 0.01,
							"pivot": [-2.5, 30.10589, 3.97001],
							"rotation": [-180, -85, -180],
							"uv": {
								"north": {"uv": [114.66667, 22.66667], "uv_size": [0, 48]},
								"east": {"uv": [12, 0], "uv_size": [-12, 48]},
								"south": {"uv": [114.66667, 22.66667], "uv_size": [0, 48]},
								"west": {"uv": [0, 0], "uv_size": [12, 48]},
								"up": {"uv": [116, 24], "uv_size": [0, 8]},
								"down": {"uv": [116, 32], "uv_size": [0, -8]}
							}
						},
						{
							"origin": [-3.5, 15.10589, -1.52999],
							"size": [7, 10, 5],
							"uv": {
								"north": {"uv": [81.33333, 60], "uv_size": [9.33333, 13.33333]},
								"east": {"uv": [74.66667, 60], "uv_size": [6.66667, 13.33333]},
								"south": {"uv": [97.33333, 60], "uv_size": [9.33333, 13.33333]},
								"west": {"uv": [90.66667, 60], "uv_size": [6.66667, 13.33333]},
								"up": {"uv": [81.33333, 53.33333], "uv_size": [9.33333, 6.66667]},
								"down": {"uv": [90.66667, 60], "uv_size": [9.33333, -6.66667]}
							}
						},
						{
							"origin": [-3.5, 16.10589, -1.52999],
							"size": [7, 4, 5],
							"inflate": 0.25,
							"uv": {
								"north": {"uv": [21.33333, 20], "uv_size": [9.33333, 5.33333]},
								"east": {"uv": [14.66667, 20], "uv_size": [6.66667, 5.33333]},
								"south": {"uv": [37.33333, 20], "uv_size": [9.33333, 5.33333]},
								"west": {"uv": [30.66667, 20], "uv_size": [6.66667, 5.33333]},
								"up": {"uv": [21.33333, 13.33333], "uv_size": [9.33333, 6.66667]},
								"down": {"uv": [30.66667, 20], "uv_size": [9.33333, -6.66667]}
							}
						}
					]
				},
				{
					"name": "head",
					"parent": "body",
					"pivot": [0, 35.22605, 1.47001],
					"cubes": [
						{
							"origin": [-3, 35.10589, -2.02999],
							"size": [6, 9, 7],
							"uv": {
								"north": {"uv": [100, 9.33333], "uv_size": [8, 12]},
								"east": {"uv": [90.66667, 9.33333], "uv_size": [9.33333, 12]},
								"south": {"uv": [117.33333, 9.33333], "uv_size": [8, 12]},
								"west": {"uv": [108, 9.33333], "uv_size": [9.33333, 12]},
								"up": {"uv": [100, 0], "uv_size": [8, 9.33333]},
								"down": {"uv": [108, 9.33333], "uv_size": [8, -9.33333]}
							}
						},
						{
							"origin": [3, 40.10589, 0.97001],
							"size": [6, 2, 2],
							"inflate": 0.01,
							"uv": {
								"north": {"uv": [94.66667, 29.33333], "uv_size": [8, 2.66667]},
								"east": {"uv": [92, 29.33333], "uv_size": [2.66667, 2.66667]},
								"south": {"uv": [105.33333, 29.33333], "uv_size": [8, 2.66667]},
								"west": {"uv": [102.66667, 29.33333], "uv_size": [2.66667, 2.66667]},
								"up": {"uv": [94.66667, 26.66667], "uv_size": [8, 2.66667]},
								"down": {"uv": [102.66667, 29.33333], "uv_size": [8, -2.66667]}
							}
						},
						{
							"origin": [8, 40.10589, 0.97001],
							"size": [1, 4, 2],
							"pivot": [9, 40.10589, 1.97001],
							"rotation": [0, 0, 20],
							"uv": {
								"north": {"uv": [102.66667, 36], "uv_size": [1.33333, 5.33333]},
								"east": {"uv": [100, 36], "uv_size": [2.66667, 5.33333]},
								"south": {"uv": [106.66667, 36], "uv_size": [1.33333, 5.33333]},
								"west": {"uv": [104, 36], "uv_size": [2.66667, 5.33333]},
								"up": {"uv": [102.66667, 33.33333], "uv_size": [1.33333, 2.66667]},
								"down": {"uv": [104, 36], "uv_size": [1.33333, -2.66667]}
							}
						},
						{
							"origin": [-9, 40.10589, 0.97001],
							"size": [1, 4, 2],
							"pivot": [-9, 40.10589, 1.97001],
							"rotation": [0, 0, -20],
							"uv": {
								"north": {"uv": [104, 36], "uv_size": [-1.33333, 5.33333]},
								"east": {"uv": [106.66667, 36], "uv_size": [-2.66667, 5.33333]},
								"south": {"uv": [108, 36], "uv_size": [-1.33333, 5.33333]},
								"west": {"uv": [102.66667, 36], "uv_size": [-2.66667, 5.33333]},
								"up": {"uv": [104, 33.33333], "uv_size": [-1.33333, 2.66667]},
								"down": {"uv": [105.33333, 36], "uv_size": [-1.33333, -2.66667]}
							}
						},
						{
							"origin": [-9, 40.10589, 0.97001],
							"size": [6, 2, 2],
							"inflate": 0.01,
							"uv": {
								"north": {"uv": [102.66667, 29.33333], "uv_size": [-8, 2.66667]},
								"east": {"uv": [105.33333, 29.33333], "uv_size": [-2.66667, 2.66667]},
								"south": {"uv": [113.33333, 29.33333], "uv_size": [-8, 2.66667]},
								"west": {"uv": [94.66667, 29.33333], "uv_size": [-2.66667, 2.66667]},
								"up": {"uv": [102.66667, 26.66667], "uv_size": [-8, 2.66667]},
								"down": {"uv": [110.66667, 29.33333], "uv_size": [-8, -2.66667]}
							}
						}
					]
				},
				{
					"name": "arm",
					"parent": "body",
					"pivot": [4, 30.10589, 1.97001],
					"rotation": [0, 0, -7.5],
					"cubes": [
						{
							"origin": [3.5, 27.10589, -0.52999],
							"size": [3, 5, 5],
							"pivot": [4, 30.10589, -2.02999],
							"rotation": [0, 0, -17.5],
							"uv": {
								"north": {"uv": [96, 86.66667], "uv_size": [4, 6.66667]},
								"east": {"uv": [89.33333, 86.66667], "uv_size": [6.66667, 6.66667]},
								"south": {"uv": [106.66667, 86.66667], "uv_size": [4, 6.66667]},
								"west": {"uv": [100, 86.66667], "uv_size": [6.66667, 6.66667]},
								"up": {"uv": [96, 80], "uv_size": [4, 6.66667]},
								"down": {"uv": [100, 86.66667], "uv_size": [4, -6.66667]}
							}
						},
						{
							"origin": [4.5, 21.10589, -0.02999],
							"size": [2, 8, 4],
							"uv": {
								"north": {"uv": [77.33333, 81.33333], "uv_size": [2.66667, 10.66667]},
								"east": {"uv": [72, 81.33333], "uv_size": [5.33333, 10.66667]},
								"south": {"uv": [85.33333, 81.33333], "uv_size": [2.66667, 10.66667]},
								"west": {"uv": [80, 81.33333], "uv_size": [5.33333, 10.66667]},
								"up": {"uv": [77.33333, 76], "uv_size": [2.66667, 5.33333]},
								"down": {"uv": [80, 81.33333], "uv_size": [2.66667, -5.33333]}
							}
						},
						{
							"origin": [4.5, 9.10589, 0.47001],
							"size": [2, 12, 3],
							"uv": {
								"north": {"uv": [77.33333, 96], "uv_size": [2.66667, 16]},
								"east": {"uv": [73.33333, 96], "uv_size": [4, 16]},
								"south": {"uv": [84, 96], "uv_size": [2.66667, 16]},
								"west": {"uv": [80, 96], "uv_size": [4, 16]},
								"up": {"uv": [77.33333, 92], "uv_size": [2.66667, 4]},
								"down": {"uv": [80, 96], "uv_size": [2.66667, -4]}
							}
						},
						{
							"origin": [5.5, 8.10589, -0.52999],
							"size": [5, 1, 5],
							"inflate": 0.01,
							"uv": {
								"north": {"uv": [50.66667, 97.33333], "uv_size": [6.66667, 1.33333]},
								"east": {"uv": [44, 97.33333], "uv_size": [6.66667, 1.33333]},
								"south": {"uv": [64, 97.33333], "uv_size": [6.66667, 1.33333]},
								"west": {"uv": [57.33333, 97.33333], "uv_size": [6.66667, 1.33333]},
								"up": {"uv": [50.66667, 90.66667], "uv_size": [6.66667, 6.66667]},
								"down": {"uv": [57.33333, 97.33333], "uv_size": [6.66667, -6.66667]}
							}
						},
						{
							"origin": [10.5, 8.10589, -0.52999],
							"size": [4, 1, 1],
							"pivot": [10.5, 9.10589, 1.97001],
							"rotation": [0, 0, 37.5],
							"uv": {
								"north": {"uv": [38.66667, 102.66667], "uv_size": [5.33333, 1.33333]},
								"east": {"uv": [37.33333, 102.66667], "uv_size": [1.33333, 1.33333]},
								"south": {"uv": [45.33333, 102.66667], "uv_size": [5.33333, 1.33333]},
								"west": {"uv": [44, 102.66667], "uv_size": [1.33333, 1.33333]},
								"up": {"uv": [38.66667, 101.33333], "uv_size": [5.33333, 1.33333]},
								"down": {"uv": [44, 102.66667], "uv_size": [5.33333, -1.33333]}
							}
						},
						{
							"origin": [10.5, 8.10589, 3.47001],
							"size": [4, 1, 1],
							"pivot": [10.5, 9.10589, 1.97001],
							"rotation": [0, 0, 37.5],
							"uv": {
								"north": {"uv": [38.66667, 102.66667], "uv_size": [5.33333, 1.33333]},
								"east": {"uv": [37.33333, 102.66667], "uv_size": [1.33333, 1.33333]},
								"south": {"uv": [45.33333, 102.66667], "uv_size": [5.33333, 1.33333]},
								"west": {"uv": [44, 102.66667], "uv_size": [1.33333, 1.33333]},
								"up": {"uv": [38.66667, 101.33333], "uv_size": [5.33333, 1.33333]},
								"down": {"uv": [44, 102.66667], "uv_size": [5.33333, -1.33333]}
							}
						},
						{
							"origin": [10.5, 8.10589, 2.17001],
							"size": [4, 1, 1],
							"pivot": [10.5, 9.10589, 1.97001],
							"rotation": [0, 0, 20],
							"uv": {
								"north": {"uv": [38.66667, 102.66667], "uv_size": [5.33333, 1.33333]},
								"east": {"uv": [37.33333, 102.66667], "uv_size": [1.33333, 1.33333]},
								"south": {"uv": [45.33333, 102.66667], "uv_size": [5.33333, 1.33333]},
								"west": {"uv": [44, 102.66667], "uv_size": [1.33333, 1.33333]},
								"up": {"uv": [38.66667, 101.33333], "uv_size": [5.33333, 1.33333]},
								"down": {"uv": [44, 102.66667], "uv_size": [5.33333, -1.33333]}
							}
						},
						{
							"origin": [10.5, 8.10589, 0.87001],
							"size": [4, 1, 1],
							"pivot": [10.5, 9.10589, 1.97001],
							"rotation": [0, 0, 22.5],
							"uv": {
								"north": {"uv": [38.66667, 102.66667], "uv_size": [5.33333, 1.33333]},
								"east": {"uv": [37.33333, 102.66667], "uv_size": [1.33333, 1.33333]},
								"south": {"uv": [45.33333, 102.66667], "uv_size": [5.33333, 1.33333]},
								"west": {"uv": [44, 102.66667], "uv_size": [1.33333, 1.33333]},
								"up": {"uv": [38.66667, 101.33333], "uv_size": [5.33333, 1.33333]},
								"down": {"uv": [44, 102.66667], "uv_size": [5.33333, -1.33333]}
							}
						},
						{
							"origin": [5.5, 8.10589, -3.52999],
							"size": [2, 1, 3],
							"inflate": -0.01,
							"pivot": [5.5, 8.60589, -0.52999],
							"rotation": [0, -17.5, 0],
							"uv": {
								"north": {"uv": [40, 94.66667], "uv_size": [2.66667, 1.33333]},
								"east": {"uv": [36, 94.66667], "uv_size": [4, 1.33333]},
								"south": {"uv": [46.66667, 94.66667], "uv_size": [2.66667, 1.33333]},
								"west": {"uv": [42.66667, 94.66667], "uv_size": [4, 1.33333]},
								"up": {"uv": [40, 90.66667], "uv_size": [2.66667, 4]},
								"down": {"uv": [42.66667, 94.66667], "uv_size": [2.66667, -4]}
							}
						}
					]
				},
				{
					"name": "arm2",
					"parent": "body",
					"pivot": [-4, 30.10589, 1.97001],
					"rotation": [0, 0, 7.5],
					"cubes": [
						{
							"origin": [-6.5, 27.10589, -0.52999],
							"size": [3, 5, 5],
							"pivot": [-4, 30.10589, -2.02999],
							"rotation": [0, 0, 17.5],
							"uv": {
								"north": {"uv": [110.66667, 101.33333], "uv_size": [-4, 6.66667]},
								"east": {"uv": [117.33333, 101.33333], "uv_size": [-6.66667, 6.66667]},
								"south": {"uv": [121.33333, 101.33333], "uv_size": [-4, 6.66667]},
								"west": {"uv": [106.66667, 101.33333], "uv_size": [-6.66667, 6.66667]},
								"up": {"uv": [110.66667, 94.66667], "uv_size": [-4, 6.66667]},
								"down": {"uv": [114.66667, 101.33333], "uv_size": [-4, -6.66667]}
							}
						},
						{
							"origin": [-6.5, 21.10589, -0.02999],
							"size": [2, 8, 4],
							"uv": {
								"north": {"uv": [102.66667, 113.33333], "uv_size": [-2.66667, 10.66667]},
								"east": {"uv": [108, 113.33333], "uv_size": [-5.33333, 10.66667]},
								"south": {"uv": [110.66667, 113.33333], "uv_size": [-2.66667, 10.66667]},
								"west": {"uv": [100, 113.33333], "uv_size": [-5.33333, 10.66667]},
								"up": {"uv": [102.66667, 108], "uv_size": [-2.66667, 5.33333]},
								"down": {"uv": [105.33333, 113.33333], "uv_size": [-2.66667, -5.33333]}
							}
						},
						{
							"origin": [-6.5, 9.10589, 0.47001],
							"size": [2, 12, 3],
							"uv": {
								"north": {"uv": [93.33333, 97.33333], "uv_size": [-2.66667, 16]},
								"east": {"uv": [97.33333, 97.33333], "uv_size": [-4, 16]},
								"south": {"uv": [100, 97.33333], "uv_size": [-2.66667, 16]},
								"west": {"uv": [90.66667, 97.33333], "uv_size": [-4, 16]},
								"up": {"uv": [93.33333, 93.33333], "uv_size": [-2.66667, 4]},
								"down": {"uv": [96, 97.33333], "uv_size": [-2.66667, -4]}
							}
						},
						{
							"origin": [-10.5, 8.10589, -0.52999],
							"size": [5, 1, 5],
							"inflate": 0.01,
							"uv": {
								"north": {"uv": [57.33333, 112], "uv_size": [-6.66667, 1.33333]},
								"east": {"uv": [64, 112], "uv_size": [-6.66667, 1.33333]},
								"south": {"uv": [70.66667, 112], "uv_size": [-6.66667, 1.33333]},
								"west": {"uv": [50.66667, 112], "uv_size": [-6.66667, 1.33333]},
								"up": {"uv": [57.33333, 105.33333], "uv_size": [-6.66667, 6.66667]},
								"down": {"uv": [64, 112], "uv_size": [-6.66667, -6.66667]}
							}
						},
						{
							"origin": [-14.5, 8.10589, -0.52999],
							"size": [4, 1, 1],
							"pivot": [-10.5, 9.10589, 1.97001],
							"rotation": [0, 0, -37.5],
							"uv": {
								"north": {"uv": [44, 102.66667], "uv_size": [-5.33333, 1.33333]},
								"east": {"uv": [45.33333, 102.66667], "uv_size": [-1.33333, 1.33333]},
								"south": {"uv": [50.66667, 102.66667], "uv_size": [-5.33333, 1.33333]},
								"west": {"uv": [38.66667, 102.66667], "uv_size": [-1.33333, 1.33333]},
								"up": {"uv": [44, 101.33333], "uv_size": [-5.33333, 1.33333]},
								"down": {"uv": [49.33333, 102.66667], "uv_size": [-5.33333, -1.33333]}
							}
						},
						{
							"origin": [-14.5, 8.10589, 3.47001],
							"size": [4, 1, 1],
							"pivot": [-10.5, 9.10589, 1.97001],
							"rotation": [0, 0, -37.5],
							"uv": {
								"north": {"uv": [44, 102.66667], "uv_size": [-5.33333, 1.33333]},
								"east": {"uv": [45.33333, 102.66667], "uv_size": [-1.33333, 1.33333]},
								"south": {"uv": [50.66667, 102.66667], "uv_size": [-5.33333, 1.33333]},
								"west": {"uv": [38.66667, 102.66667], "uv_size": [-1.33333, 1.33333]},
								"up": {"uv": [44, 101.33333], "uv_size": [-5.33333, 1.33333]},
								"down": {"uv": [49.33333, 102.66667], "uv_size": [-5.33333, -1.33333]}
							}
						},
						{
							"origin": [-14.5, 8.10589, 2.17001],
							"size": [4, 1, 1],
							"pivot": [-10.5, 9.10589, 1.97001],
							"rotation": [0, 0, -20],
							"uv": {
								"north": {"uv": [44, 102.66667], "uv_size": [-5.33333, 1.33333]},
								"east": {"uv": [45.33333, 102.66667], "uv_size": [-1.33333, 1.33333]},
								"south": {"uv": [50.66667, 102.66667], "uv_size": [-5.33333, 1.33333]},
								"west": {"uv": [38.66667, 102.66667], "uv_size": [-1.33333, 1.33333]},
								"up": {"uv": [44, 101.33333], "uv_size": [-5.33333, 1.33333]},
								"down": {"uv": [49.33333, 102.66667], "uv_size": [-5.33333, -1.33333]}
							}
						},
						{
							"origin": [-14.5, 8.10589, 0.87001],
							"size": [4, 1, 1],
							"pivot": [-10.5, 9.10589, 1.97001],
							"rotation": [0, 0, -22.5],
							"uv": {
								"north": {"uv": [44, 102.66667], "uv_size": [-5.33333, 1.33333]},
								"east": {"uv": [45.33333, 102.66667], "uv_size": [-1.33333, 1.33333]},
								"south": {"uv": [50.66667, 102.66667], "uv_size": [-5.33333, 1.33333]},
								"west": {"uv": [38.66667, 102.66667], "uv_size": [-1.33333, 1.33333]},
								"up": {"uv": [44, 101.33333], "uv_size": [-5.33333, 1.33333]},
								"down": {"uv": [49.33333, 102.66667], "uv_size": [-5.33333, -1.33333]}
							}
						},
						{
							"origin": [-7.5, 8.10589, -3.52999],
							"size": [2, 1, 3],
							"inflate": -0.01,
							"pivot": [-5.5, 8.60589, -0.52999],
							"rotation": [0, 17.5, 0],
							"uv": {
								"north": {"uv": [42.66667, 94.66667], "uv_size": [-2.66667, 1.33333]},
								"east": {"uv": [46.66667, 94.66667], "uv_size": [-4, 1.33333]},
								"south": {"uv": [49.33333, 94.66667], "uv_size": [-2.66667, 1.33333]},
								"west": {"uv": [40, 94.66667], "uv_size": [-4, 1.33333]},
								"up": {"uv": [42.66667, 90.66667], "uv_size": [-2.66667, 4]},
								"down": {"uv": [45.33333, 94.66667], "uv_size": [-2.66667, -4]}
							}
						}
					]
				},
				{
					"name": "leg",
					"parent": "entity",
					"pivot": [2, 15.15589, 0.97001],
					"rotation": [0, -5, 0],
					"cubes": [
						{
							"origin": [0.5, 3.10589, -1.02999],
							"size": [3, 12, 4],
							"uv": {
								"north": {"uv": [21.33333, 41.33333], "uv_size": [4, 16]},
								"east": {"uv": [16, 41.33333], "uv_size": [5.33333, 16]},
								"south": {"uv": [30.66667, 41.33333], "uv_size": [4, 16]},
								"west": {"uv": [25.33333, 41.33333], "uv_size": [5.33333, 16]},
								"up": {"uv": [21.33333, 36], "uv_size": [4, 5.33333]},
								"down": {"uv": [25.33333, 41.33333], "uv_size": [4, -5.33333]}
							}
						},
						{
							"origin": [0.5, 10.10589, -1.02999],
							"size": [3, 3, 4],
							"inflate": 0.2,
							"uv": {
								"north": {"uv": [5.33333, 60], "uv_size": [4, 4]},
								"east": {"uv": [0, 60], "uv_size": [5.33333, 4]},
								"south": {"uv": [14.66667, 60], "uv_size": [4, 4]},
								"west": {"uv": [9.33333, 60], "uv_size": [5.33333, 4]},
								"up": {"uv": [5.33333, 54.66667], "uv_size": [4, 5.33333]},
								"down": {"uv": [9.33333, 60], "uv_size": [4, -5.33333]}
							}
						},
						{
							"origin": [0, 0.10589, -6.02999],
							"size": [4, 3, 9],
							"uv": {
								"north": {"uv": [45.33333, 68], "uv_size": [5.33333, 4]},
								"east": {"uv": [33.33333, 68], "uv_size": [12, 4]},
								"south": {"uv": [62.66667, 68], "uv_size": [5.33333, 4]},
								"west": {"uv": [50.66667, 68], "uv_size": [12, 4]},
								"up": {"uv": [45.33333, 56], "uv_size": [5.33333, 12]},
								"down": {"uv": [50.66667, 68], "uv_size": [5.33333, -12]}
							}
						}
					]
				},
				{
					"name": "leg2",
					"parent": "entity",
					"pivot": [-2, 15.15589, 0.97001],
					"rotation": [0, 5, 0],
					"cubes": [
						{
							"origin": [-3.5, 3.10589, -1.02999],
							"size": [3, 12, 4],
							"uv": {
								"north": {"uv": [16, 73.33333], "uv_size": [-4, 16]},
								"east": {"uv": [21.33333, 73.33333], "uv_size": [-5.33333, 16]},
								"south": {"uv": [25.33333, 73.33333], "uv_size": [-4, 16]},
								"west": {"uv": [12, 73.33333], "uv_size": [-5.33333, 16]},
								"up": {"uv": [16, 68], "uv_size": [-4, 5.33333]},
								"down": {"uv": [20, 73.33333], "uv_size": [-4, -5.33333]}
							}
						},
						{
							"origin": [-4, 0.10589, -6.02999],
							"size": [4, 3, 9],
							"uv": {
								"north": {"uv": [50.66667, 84], "uv_size": [-5.33333, 4]},
								"east": {"uv": [62.66667, 84], "uv_size": [-12, 4]},
								"south": {"uv": [68, 84], "uv_size": [-5.33333, 4]},
								"west": {"uv": [45.33333, 84], "uv_size": [-12, 4]},
								"up": {"uv": [50.66667, 72], "uv_size": [-5.33333, 12]},
								"down": {"uv": [56, 84], "uv_size": [-5.33333, -12]}
							}
						}
					]
				}
			]
		}
	]
}