{
	"format_version": "1.12.0",
	"minecraft:geometry": [
		{
			"description": {
				"identifier": "geometry.unknown",
				"texture_width": 96,
				"texture_height": 96,
				"visible_bounds_width": 6,
				"visible_bounds_height": 4.5,
				"visible_bounds_offset": [0, 1.75, 0]
			},
			"bones": [
				{
					"name": "entity",
					"pivot": [0, 0, 0]
				},
				{
					"name": "leg4",
					"parent": "entity",
					"pivot": [-3.915, 14.7, 5.94],
					"rotation": [0, 37.5, 0],
					"cubes": [
						{
							"origin": [-14.715, -0.15, 1.89],
							"size": [5.4, 18.9, 8.1],
							"uv": {
								"north": {"uv": [9, 42], "uv_size": [4, 14]},
								"east": {"uv": [3, 42], "uv_size": [6, 14]},
								"south": {"uv": [19, 42], "uv_size": [4, 14]},
								"west": {"uv": [13, 42], "uv_size": [6, 14]},
								"up": {"uv": [9, 36], "uv_size": [4, 6]},
								"down": {"uv": [13, 42], "uv_size": [4, -6]}
							}
						},
						{
							"origin": [-13.365, -0.15, 9.99],
							"size": [4.05, 4.05, 5.4],
							"uv": {
								"north": {"uv": [5, 26], "uv_size": [3, 3]},
								"east": {"uv": [1, 26], "uv_size": [4, 3]},
								"south": {"uv": [12, 26], "uv_size": [3, 3]},
								"west": {"uv": [8, 26], "uv_size": [4, 3]},
								"up": {"uv": [5, 22], "uv_size": [3, 4]},
								"down": {"uv": [8, 26], "uv_size": [3, -4]}
							}
						},
						{
							"origin": [-13.365, -0.15, -3.51],
							"size": [4.05, 4.05, 5.4],
							"uv": {
								"north": {"uv": [5, 26], "uv_size": [3, 3]},
								"east": {"uv": [1, 26], "uv_size": [4, 3]},
								"south": {"uv": [12, 26], "uv_size": [3, 3]},
								"west": {"uv": [8, 26], "uv_size": [4, 3]},
								"up": {"uv": [5, 22], "uv_size": [3, 4]},
								"down": {"uv": [8, 26], "uv_size": [3, -4]}
							}
						},
						{
							"origin": [-21.465, -0.15, 3.24],
							"size": [6.75, 4.05, 5.4],
							"uv": {
								"north": {"uv": [31, 39], "uv_size": [5, 3]},
								"east": {"uv": [27, 39], "uv_size": [4, 3]},
								"south": {"uv": [40, 39], "uv_size": [5, 3]},
								"west": {"uv": [36, 39], "uv_size": [4, 3]},
								"up": {"uv": [31, 35], "uv_size": [5, 4]},
								"down": {"uv": [36, 39], "uv_size": [5, -4]}
							}
						},
						{
							"origin": [-10.665, 12, 3.24],
							"size": [9.45, 4.05, 5.4],
							"pivot": [-6.615, 14.025, 5.94],
							"rotation": [0, 0, -12.5],
							"uv": {
								"north": {"uv": [4, 33], "uv_size": [7, 3]},
								"east": {"uv": [0, 33], "uv_size": [4, 3]},
								"south": {"uv": [15, 33], "uv_size": [7, 3]},
								"west": {"uv": [11, 33], "uv_size": [4, 3]},
								"up": {"uv": [4, 29], "uv_size": [7, 4]},
								"down": {"uv": [11, 33], "uv_size": [7, -4]}
							}
						}
					]
				},
				{
					"name": "leg3",
					"parent": "entity",
					"pivot": [3.915, 14.7, 5.94],
					"rotation": [0, -37.5, 0],
					"cubes": [
						{
							"origin": [9.315, -0.15, 1.89],
							"size": [5.4, 18.9, 8.1],
							"uv": {
								"north": {"uv": [13, 42], "uv_size": [-4, 14]},
								"east": {"uv": [19, 42], "uv_size": [-6, 14]},
								"south": {"uv": [23, 42], "uv_size": [-4, 14]},
								"west": {"uv": [9, 42], "uv_size": [-6, 14]},
								"up": {"uv": [13, 36], "uv_size": [-4, 6]},
								"down": {"uv": [17, 42], "uv_size": [-4, -6]}
							}
						},
						{
							"origin": [9.315, -0.15, 9.99],
							"size": [4.05, 4.05, 5.4],
							"uv": {
								"north": {"uv": [8, 26], "uv_size": [-3, 3]},
								"east": {"uv": [12, 26], "uv_size": [-4, 3]},
								"south": {"uv": [15, 26], "uv_size": [-3, 3]},
								"west": {"uv": [5, 26], "uv_size": [-4, 3]},
								"up": {"uv": [8, 22], "uv_size": [-3, 4]},
								"down": {"uv": [11, 26], "uv_size": [-3, -4]}
							}
						},
						{
							"origin": [9.315, -0.15, -3.51],
							"size": [4.05, 4.05, 5.4],
							"uv": {
								"north": {"uv": [8, 26], "uv_size": [-3, 3]},
								"east": {"uv": [12, 26], "uv_size": [-4, 3]},
								"south": {"uv": [15, 26], "uv_size": [-3, 3]},
								"west": {"uv": [5, 26], "uv_size": [-4, 3]},
								"up": {"uv": [8, 22], "uv_size": [-3, 4]},
								"down": {"uv": [11, 26], "uv_size": [-3, -4]}
							}
						},
						{
							"origin": [14.715, -0.15, 3.24],
							"size": [6.75, 4.05, 5.4],
							"uv": {
								"north": {"uv": [36, 39], "uv_size": [-5, 3]},
								"east": {"uv": [40, 39], "uv_size": [-4, 3]},
								"south": {"uv": [45, 39], "uv_size": [-5, 3]},
								"west": {"uv": [31, 39], "uv_size": [-4, 3]},
								"up": {"uv": [36, 35], "uv_size": [-5, 4]},
								"down": {"uv": [41, 39], "uv_size": [-5, -4]}
							}
						},
						{
							"origin": [1.215, 12, 3.24],
							"size": [9.45, 4.05, 5.4],
							"pivot": [6.615, 14.025, 5.94],
							"rotation": [0, 0, 12.5],
							"uv": {
								"north": {"uv": [11, 33], "uv_size": [-7, 3]},
								"east": {"uv": [15, 33], "uv_size": [-4, 3]},
								"south": {"uv": [22, 33], "uv_size": [-7, 3]},
								"west": {"uv": [4, 33], "uv_size": [-4, 3]},
								"up": {"uv": [11, 29], "uv_size": [-7, 4]},
								"down": {"uv": [18, 33], "uv_size": [-7, -4]}
							}
						}
					]
				},
				{
					"name": "leg2",
					"parent": "entity",
					"pivot": [-3.915, 14.7, -1.62],
					"rotation": [0, -37.5, 0],
					"cubes": [
						{
							"origin": [-14.715, -0.15, -5.67],
							"size": [5.4, 18.9, 8.1],
							"uv": {
								"north": {"uv": [9, 42], "uv_size": [4, 14]},
								"east": {"uv": [3, 42], "uv_size": [6, 14]},
								"south": {"uv": [19, 42], "uv_size": [4, 14]},
								"west": {"uv": [13, 42], "uv_size": [6, 14]},
								"up": {"uv": [9, 36], "uv_size": [4, 6]},
								"down": {"uv": [13, 42], "uv_size": [4, -6]}
							}
						},
						{
							"origin": [-13.365, -0.15, -11.07],
							"size": [4.05, 4.05, 5.4],
							"uv": {
								"north": {"uv": [5, 26], "uv_size": [3, 3]},
								"east": {"uv": [1, 26], "uv_size": [4, 3]},
								"south": {"uv": [12, 26], "uv_size": [3, 3]},
								"west": {"uv": [8, 26], "uv_size": [4, 3]},
								"up": {"uv": [5, 22], "uv_size": [3, 4]},
								"down": {"uv": [8, 26], "uv_size": [3, -4]}
							}
						},
						{
							"origin": [-13.365, -0.15, 2.43],
							"size": [4.05, 4.05, 5.4],
							"uv": {
								"north": {"uv": [5, 26], "uv_size": [3, 3]},
								"east": {"uv": [1, 26], "uv_size": [4, 3]},
								"south": {"uv": [12, 26], "uv_size": [3, 3]},
								"west": {"uv": [8, 26], "uv_size": [4, 3]},
								"up": {"uv": [5, 22], "uv_size": [3, 4]},
								"down": {"uv": [8, 26], "uv_size": [3, -4]}
							}
						},
						{
							"origin": [-21.465, -0.15, -4.32],
							"size": [6.75, 4.05, 5.4],
							"uv": {
								"north": {"uv": [31, 39], "uv_size": [5, 3]},
								"east": {"uv": [27, 39], "uv_size": [4, 3]},
								"south": {"uv": [40, 39], "uv_size": [5, 3]},
								"west": {"uv": [36, 39], "uv_size": [4, 3]},
								"up": {"uv": [31, 35], "uv_size": [5, 4]},
								"down": {"uv": [36, 39], "uv_size": [5, -4]}
							}
						},
						{
							"origin": [-10.665, 12, -4.32],
							"size": [8.1, 4.05, 5.4],
							"pivot": [-6.615, 14.025, -1.62],
							"rotation": [0, 0, -12.5],
							"uv": {
								"north": {"uv": [5, 33], "uv_size": [6, 3]},
								"east": {"uv": [1, 33], "uv_size": [4, 3]},
								"south": {"uv": [15, 33], "uv_size": [6, 3]},
								"west": {"uv": [11, 33], "uv_size": [4, 3]},
								"up": {"uv": [5, 29], "uv_size": [6, 4]},
								"down": {"uv": [11, 33], "uv_size": [6, -4]}
							}
						}
					]
				},
				{
					"name": "leg",
					"parent": "entity",
					"pivot": [3.915, 14.7, -1.62],
					"rotation": [0, 37.5, 0],
					"cubes": [
						{
							"origin": [9.315, -0.15, -5.67],
							"size": [5.4, 18.9, 8.1],
							"uv": {
								"north": {"uv": [13, 42], "uv_size": [-4, 14]},
								"east": {"uv": [19, 42], "uv_size": [-6, 14]},
								"south": {"uv": [23, 42], "uv_size": [-4, 14]},
								"west": {"uv": [9, 42], "uv_size": [-6, 14]},
								"up": {"uv": [13, 36], "uv_size": [-4, 6]},
								"down": {"uv": [17, 42], "uv_size": [-4, -6]}
							}
						},
						{
							"origin": [9.315, -0.15, -11.07],
							"size": [4.05, 4.05, 5.4],
							"uv": {
								"north": {"uv": [8, 26], "uv_size": [-3, 3]},
								"east": {"uv": [12, 26], "uv_size": [-4, 3]},
								"south": {"uv": [15, 26], "uv_size": [-3, 3]},
								"west": {"uv": [5, 26], "uv_size": [-4, 3]},
								"up": {"uv": [8, 22], "uv_size": [-3, 4]},
								"down": {"uv": [11, 26], "uv_size": [-3, -4]}
							}
						},
						{
							"origin": [9.315, -0.15, 2.43],
							"size": [4.05, 4.05, 5.4],
							"uv": {
								"north": {"uv": [8, 26], "uv_size": [-3, 3]},
								"east": {"uv": [12, 26], "uv_size": [-4, 3]},
								"south": {"uv": [15, 26], "uv_size": [-3, 3]},
								"west": {"uv": [5, 26], "uv_size": [-4, 3]},
								"up": {"uv": [8, 22], "uv_size": [-3, 4]},
								"down": {"uv": [11, 26], "uv_size": [-3, -4]}
							}
						},
						{
							"origin": [14.715, -0.15, -4.32],
							"size": [6.75, 4.05, 5.4],
							"uv": {
								"north": {"uv": [36, 39], "uv_size": [-5, 3]},
								"east": {"uv": [40, 39], "uv_size": [-4, 3]},
								"south": {"uv": [45, 39], "uv_size": [-5, 3]},
								"west": {"uv": [31, 39], "uv_size": [-4, 3]},
								"up": {"uv": [36, 35], "uv_size": [-5, 4]},
								"down": {"uv": [41, 39], "uv_size": [-5, -4]}
							}
						},
						{
							"origin": [2.565, 12, -4.32],
							"size": [8.1, 4.05, 5.4],
							"pivot": [6.615, 14.025, -1.62],
							"rotation": [0, 0, 12.5],
							"uv": {
								"north": {"uv": [11, 33], "uv_size": [-6, 3]},
								"east": {"uv": [15, 33], "uv_size": [-4, 3]},
								"south": {"uv": [21, 33], "uv_size": [-6, 3]},
								"west": {"uv": [5, 33], "uv_size": [-4, 3]},
								"up": {"uv": [11, 29], "uv_size": [-6, 4]},
								"down": {"uv": [17, 33], "uv_size": [-6, -4]}
							}
						}
					]
				},
				{
					"name": "body",
					"parent": "entity",
					"pivot": [0, 13.35, 1.35],
					"cubes": [
						{
							"origin": [-9.45, 24.15, -5.4],
							"size": [18.9, 13.5, 13.5],
							"uv": {
								"north": {"uv": [10, 11], "uv_size": [14, 10]},
								"east": {"uv": [0, 11], "uv_size": [10, 10]},
								"south": {"uv": [34, 11], "uv_size": [14, 10]},
								"west": {"uv": [24, 11], "uv_size": [10, 10]},
								"up": {"uv": [10, 1], "uv_size": [14, 10]},
								"down": {"uv": [24, 11], "uv_size": [14, -10]}
							}
						},
						{
							"origin": [-24.66094, 34.71684, 3.88064],
							"size": [17.55, 2.7, 6.75],
							"pivot": [-7.425, 34.92577, 7.1537],
							"rotation": [-48.93775, 14.90146, 22.5164],
							"uv": {
								"north": {"uv": [49, 5], "uv_size": [13, 2]},
								"east": {"uv": [44, 5], "uv_size": [5, 2]},
								"south": {"uv": [67, 5], "uv_size": [13, 2]},
								"west": {"uv": [62, 5], "uv_size": [5, 2]},
								"up": {"uv": [49, 0], "uv_size": [13, 5]},
								"down": {"uv": [62, 5], "uv_size": [13, -5]}
							}
						},
						{
							"origin": [7.11094, 34.71684, 3.88064],
							"size": [17.55, 2.7, 6.75],
							"pivot": [7.425, 34.92577, 7.1537],
							"rotation": [-48.93775, -14.90146, -22.5164],
							"uv": {
								"north": {"uv": [62, 5], "uv_size": [-13, 2]},
								"east": {"uv": [67, 5], "uv_size": [-5, 2]},
								"south": {"uv": [80, 5], "uv_size": [-13, 2]},
								"west": {"uv": [49, 5], "uv_size": [-5, 2]},
								"up": {"uv": [62, 0], "uv_size": [-13, 5]},
								"down": {"uv": [75, 5], "uv_size": [-13, -5]}
							}
						},
						{
							"origin": [-5.4, 12, -4.05],
							"size": [10.8, 12.15, 10.8],
							"uv": {
								"north": {"uv": [57, 29], "uv_size": [8, 9]},
								"east": {"uv": [49, 29], "uv_size": [8, 9]},
								"south": {"uv": [73, 29], "uv_size": [8, 9]},
								"west": {"uv": [65, 29], "uv_size": [8, 9]},
								"up": {"uv": [57, 21], "uv_size": [8, 8]},
								"down": {"uv": [65, 29], "uv_size": [8, -8]}
							}
						}
					]
				},
				{
					"name": "head",
					"parent": "body",
					"pivot": [0, 36.01397, -4.53202],
					"cubes": [
						{
							"origin": [-6.21, 28.875, -17.685],
							"size": [12.15, 2.7, 8.1],
							"pivot": [0, 34.96856, -6.4299],
							"rotation": [22.5, 0, 0],
							"uv": {
								"north": {"uv": [36, 60], "uv_size": [9, 2]},
								"east": {"uv": [30, 60], "uv_size": [6, 2]},
								"south": {"uv": [51, 60], "uv_size": [9, 2]},
								"west": {"uv": [45, 60], "uv_size": [6, 2]},
								"up": {"uv": [36, 54], "uv_size": [9, 6]},
								"down": {"uv": [45, 60], "uv_size": [9, -6]}
							}
						},
						{
							"origin": [-6.21, 35.625, -16.335],
							"size": [12.15, 2.7, 12.15],
							"pivot": [0, 34.96856, -6.4299],
							"rotation": [22.5, 0, 0],
							"uv": {
								"north": {"uv": [12, 65], "uv_size": [9, 2]},
								"east": {"uv": [3, 65], "uv_size": [9, 2]},
								"south": {"uv": [30, 65], "uv_size": [9, 2]},
								"west": {"uv": [21, 65], "uv_size": [9, 2]},
								"up": {"uv": [12, 56], "uv_size": [9, 9]},
								"down": {"uv": [21, 65], "uv_size": [9, -9]}
							}
						},
						{
							"origin": [-8.91, 38.79166, -5.1302],
							"size": [17.55, 0, 16.2],
							"pivot": [0, 34.96856, -6.4299],
							"rotation": [7.5, 0, 0],
							"uv": {
								"north": {"uv": [55, 51], "uv_size": [13, 0]},
								"east": {"uv": [43, 51], "uv_size": [12, 0]},
								"south": {"uv": [80, 51], "uv_size": [13, 0]},
								"west": {"uv": [68, 51], "uv_size": [12, 0]},
								"up": {"uv": [55, 39], "uv_size": [13, 12]},
								"down": {"uv": [68, 51], "uv_size": [13, -12]}
							}
						},
						{
							"origin": [-6.21, 28.875, -9.585],
							"size": [12.15, 6.75, 5.4],
							"pivot": [0, 34.96856, -6.4299],
							"rotation": [22.5, 0, 0],
							"uv": {
								"north": {"uv": [58, 15], "uv_size": [9, 5]},
								"east": {"uv": [54, 15], "uv_size": [4, 5]},
								"south": {"uv": [71, 15], "uv_size": [9, 5]},
								"west": {"uv": [67, 15], "uv_size": [4, 5]},
								"up": {"uv": [58, 11], "uv_size": [9, 4]},
								"down": {"uv": [67, 15], "uv_size": [9, -4]}
							}
						},
						{
							"origin": [-6.8175, 38.325, -17.0775],
							"size": [13.5, 4.05, 13.5],
							"pivot": [0, 34.96856, -6.4299],
							"rotation": [22.5, 0, 0],
							"uv": {
								"north": {"uv": [10, 79], "uv_size": [10, 3]},
								"east": {"uv": [0, 79], "uv_size": [10, 3]},
								"south": {"uv": [30, 79], "uv_size": [10, 3]},
								"west": {"uv": [20, 79], "uv_size": [10, 3]},
								"up": {"uv": [10, 69], "uv_size": [10, 10]},
								"down": {"uv": [20, 79], "uv_size": [10, -10]}
							}
						},
						{
							"origin": [-2.17879, 38.35863, -33.3795],
							"size": [10.807, 0.007, 18.907],
							"inflate": 0.01,
							"pivot": [0, 34.96856, -6.4299],
							"rotation": [24.14867, -20.70481, -9.00717],
							"uv": {
								"north": {"uv": [75, 66], "uv_size": [-8, 0]},
								"east": {"uv": [89, 66], "uv_size": [-14, 0]},
								"south": {"uv": [97, 66], "uv_size": [-8, 0]},
								"west": {"uv": [67, 66], "uv_size": [-14, 0]},
								"up": {"uv": [75, 52], "uv_size": [-8, 14]},
								"down": {"uv": [83, 66], "uv_size": [-8, -14]}
							}
						},
						{
							"origin": [-2.17879, 38.35863, -33.3795],
							"size": [10.807, 8.107, 0.007],
							"inflate": 0.01,
							"pivot": [0, 34.96856, -6.4299],
							"rotation": [24.14867, -20.70481, -9.00717],
							"uv": {
								"north": {"uv": [75, 67], "uv_size": [-8, 6]},
								"east": {"uv": [75, 67], "uv_size": [0, 6]},
								"south": {"uv": [83, 67], "uv_size": [-8, 6]},
								"west": {"uv": [67, 67], "uv_size": [0, 6]},
								"up": {"uv": [75, 67], "uv_size": [-8, 0]},
								"down": {"uv": [83, 67], "uv_size": [-8, 0]}
							}
						},
						{
							"origin": [-8.62821, 38.35863, -33.3795],
							"size": [10.807, 0.007, 18.907],
							"inflate": 0.01,
							"pivot": [0, 34.96856, -6.4299],
							"rotation": [24.14867, 20.70481, 9.00717],
							"uv": {
								"north": {"uv": [67, 66], "uv_size": [8, 0]},
								"east": {"uv": [53, 66], "uv_size": [14, 0]},
								"south": {"uv": [89, 66], "uv_size": [8, 0]},
								"west": {"uv": [75, 66], "uv_size": [14, 0]},
								"up": {"uv": [67, 52], "uv_size": [8, 14]},
								"down": {"uv": [75, 66], "uv_size": [8, -14]}
							}
						},
						{
							"origin": [-8.62821, 38.35863, -33.3795],
							"size": [10.807, 8.107, 0.007],
							"inflate": 0.01,
							"pivot": [0, 34.96856, -6.4299],
							"rotation": [24.14867, 20.70481, 9.00717],
							"uv": {
								"north": {"uv": [67, 67], "uv_size": [8, 6]},
								"east": {"uv": [67, 67], "uv_size": [0, 6]},
								"south": {"uv": [75, 67], "uv_size": [8, 6]},
								"west": {"uv": [75, 67], "uv_size": [0, 6]},
								"up": {"uv": [67, 67], "uv_size": [8, 0]},
								"down": {"uv": [75, 67], "uv_size": [8, 0]}
							}
						}
					]
				},
				{
					"name": "arm2",
					"parent": "body",
					"pivot": [-9.18, 32.25, 1.35],
					"rotation": [17.5, 15, 0],
					"cubes": [
						{
							"origin": [-21.93519, 28.41431, -14.97053],
							"size": [6.75, 9.45, 20.25],
							"pivot": [-16.53519, 33.13931, -1.47053],
							"rotation": [0, 17.5, 0],
							"uv": {
								"north": {"uv": [48, 89], "uv_size": [-5, 7]},
								"east": {"uv": [63, 89], "uv_size": [-15, 7]},
								"south": {"uv": [68, 89], "uv_size": [-5, 7]},
								"west": {"uv": [43, 89], "uv_size": [-15, 7]},
								"up": {"uv": [48, 74], "uv_size": [-5, 15]},
								"down": {"uv": [53, 89], "uv_size": [-5, -15]}
							}
						},
						{
							"origin": [-18.56019, 33.81431, -24.42053],
							"size": [0, 10.8, 16.2],
							"pivot": [-16.53519, 33.13931, -1.47053],
							"rotation": [0, 17.5, 0],
							"uv": {
								"north": {"uv": [12, 88], "uv_size": [0, 8]},
								"east": {"uv": [24, 88], "uv_size": [-12, 8]},
								"south": {"uv": [24, 88], "uv_size": [0, 8]},
								"west": {"uv": [12, 88], "uv_size": [-12, 8]},
								"up": {"uv": [12, 76], "uv_size": [0, 12]},
								"down": {"uv": [12, 88], "uv_size": [0, -12]}
							}
						},
						{
							"origin": [-24.65475, 37.86431, -22.85884],
							"size": [0, 10.8, 16.2],
							"pivot": [-23.57571, 35.16431, -13.47132],
							"rotation": [0, -17.5, 180],
							"uv": {
								"north": {"uv": [12, 88], "uv_size": [0, 8]},
								"east": {"uv": [24, 88], "uv_size": [-12, 8]},
								"south": {"uv": [24, 88], "uv_size": [0, 8]},
								"west": {"uv": [12, 88], "uv_size": [-12, 8]},
								"up": {"uv": [12, 76], "uv_size": [0, 12]},
								"down": {"uv": [12, 88], "uv_size": [0, -12]}
							}
						},
						{
							"origin": [-16.53519, 30.43931, -1.47053],
							"size": [8.1, 5.4, 5.4],
							"uv": {
								"north": {"uv": [86, 92], "uv_size": [-6, 4]},
								"east": {"uv": [90, 92], "uv_size": [-4, 4]},
								"south": {"uv": [96, 92], "uv_size": [-6, 4]},
								"west": {"uv": [80, 92], "uv_size": [-4, 4]},
								"up": {"uv": [86, 88], "uv_size": [-6, 4]},
								"down": {"uv": [92, 92], "uv_size": [-6, -4]}
							}
						}
					]
				},
				{
					"name": "arm",
					"parent": "body",
					"pivot": [9.18, 32.25, 1.35],
					"rotation": [17.5, -15, 0],
					"cubes": [
						{
							"origin": [15.18519, 28.41431, -14.97053],
							"size": [6.75, 9.45, 20.25],
							"pivot": [16.53519, 33.13931, -1.47053],
							"rotation": [0, -17.5, 0],
							"uv": {
								"north": {"uv": [43, 89], "uv_size": [5, 7]},
								"east": {"uv": [28, 89], "uv_size": [15, 7]},
								"south": {"uv": [63, 89], "uv_size": [5, 7]},
								"west": {"uv": [48, 89], "uv_size": [15, 7]},
								"up": {"uv": [43, 74], "uv_size": [5, 15]},
								"down": {"uv": [48, 89], "uv_size": [5, -15]}
							}
						},
						{
							"origin": [18.56019, 33.81431, -24.42053],
							"size": [0, 10.8, 16.2],
							"pivot": [16.53519, 33.13931, -1.47053],
							"rotation": [0, -17.5, 0],
							"uv": {
								"north": {"uv": [12, 88], "uv_size": [0, 8]},
								"east": {"uv": [0, 88], "uv_size": [12, 8]},
								"south": {"uv": [24, 88], "uv_size": [0, 8]},
								"west": {"uv": [12, 88], "uv_size": [12, 8]},
								"up": {"uv": [12, 76], "uv_size": [0, 12]},
								"down": {"uv": [12, 88], "uv_size": [0, -12]}
							}
						},
						{
							"origin": [24.65475, 37.86431, -22.85884],
							"size": [0, 10.8, 16.2],
							"pivot": [23.57571, 35.16431, -13.47132],
							"rotation": [0, 17.5, -180],
							"uv": {
								"north": {"uv": [12, 88], "uv_size": [0, 8]},
								"east": {"uv": [0, 88], "uv_size": [12, 8]},
								"south": {"uv": [24, 88], "uv_size": [0, 8]},
								"west": {"uv": [12, 88], "uv_size": [12, 8]},
								"up": {"uv": [12, 76], "uv_size": [0, 12]},
								"down": {"uv": [12, 88], "uv_size": [0, -12]}
							}
						},
						{
							"origin": [8.43519, 30.43931, -1.47053],
							"size": [8.1, 5.4, 5.4],
							"uv": {
								"north": {"uv": [80, 92], "uv_size": [6, 4]},
								"east": {"uv": [76, 92], "uv_size": [4, 4]},
								"south": {"uv": [90, 92], "uv_size": [6, 4]},
								"west": {"uv": [86, 92], "uv_size": [4, 4]},
								"up": {"uv": [80, 88], "uv_size": [6, 4]},
								"down": {"uv": [86, 92], "uv_size": [6, -4]}
							}
						}
					]
				},
				{
					"name": "wing",
					"parent": "body",
					"pivot": [7.425, 32.925, 8.1],
					"cubes": [
						{
							"origin": [6.75, 28.2, 8.1],
							"size": [28.35, 6.75, 0],
							"pivot": [7.425, 31.575, 8.1],
							"rotation": [-3.55831, -16.8773, 13.25402],
							"uv": {
								"north": {"uv": [54, 78], "uv_size": [21, 5]},
								"east": {"uv": [54, 78], "uv_size": [0, 5]},
								"south": {"uv": [75, 78], "uv_size": [21, 5]},
								"west": {"uv": [75, 78], "uv_size": [0, 5]},
								"up": {"uv": [54, 78], "uv_size": [21, 0]},
								"down": {"uv": [75, 78], "uv_size": [21, 0]}
							}
						},
						{
							"origin": [6.75, 26.85, 8.235],
							"size": [28.35, 6.75, 0],
							"pivot": [7.425, 31.575, 8.1],
							"rotation": [-10.47147, -13.76985, 38.99383],
							"uv": {
								"north": {"uv": [54, 78], "uv_size": [21, 5]},
								"east": {"uv": [54, 78], "uv_size": [0, 5]},
								"south": {"uv": [75, 78], "uv_size": [21, 5]},
								"west": {"uv": [75, 78], "uv_size": [0, 5]},
								"up": {"uv": [54, 78], "uv_size": [21, 0]},
								"down": {"uv": [75, 78], "uv_size": [21, 0]}
							}
						}
					]
				},
				{
					"name": "wing2",
					"parent": "body",
					"pivot": [-7.425, 32.925, 8.1],
					"cubes": [
						{
							"origin": [-35.1, 28.2, 8.1],
							"size": [28.35, 6.75, 0],
							"pivot": [-7.425, 31.575, 8.1],
							"rotation": [-3.55831, 16.8773, -13.25402],
							"uv": {
								"north": {"uv": [75, 78], "uv_size": [-21, 5]},
								"east": {"uv": [75, 78], "uv_size": [0, 5]},
								"south": {"uv": [96, 78], "uv_size": [-21, 5]},
								"west": {"uv": [54, 78], "uv_size": [0, 5]},
								"up": {"uv": [75, 78], "uv_size": [-21, 0]},
								"down": {"uv": [96, 78], "uv_size": [-21, 0]}
							}
						},
						{
							"origin": [-35.1, 26.85, 8.235],
							"size": [28.35, 6.75, 0],
							"pivot": [-7.425, 31.575, 8.1],
							"rotation": [-10.47147, 13.76985, -38.99383],
							"uv": {
								"north": {"uv": [75, 78], "uv_size": [-21, 5]},
								"east": {"uv": [75, 78], "uv_size": [0, 5]},
								"south": {"uv": [96, 78], "uv_size": [-21, 5]},
								"west": {"uv": [54, 78], "uv_size": [0, 5]},
								"up": {"uv": [75, 78], "uv_size": [-21, 0]},
								"down": {"uv": [96, 78], "uv_size": [-21, 0]}
							}
						}
					]
				}
			]
		}
	]
}