{
	"format_version": "1.12.0",
	"minecraft:geometry": [
		{
			"description": {
				"identifier": "geometry.unknown",
				"texture_width": 80,
				"texture_height": 80,
				"visible_bounds_width": 5,
				"visible_bounds_height": 5.5,
				"visible_bounds_offset": [0, 2.25, 0]
			},
			"bones": [
				{
					"name": "entity",
					"pivot": [0, 0, 0]
				},
				{
					"name": "body",
					"parent": "entity",
					"pivot": [0, 20, 0.5],
					"cubes": [
						{"origin": [-4, 16.5, -2.5], "size": [8, 7, 6], "uv": [38, 30]}
					]
				},
				{
					"name": "torso",
					"parent": "body",
					"pivot": [0, 24, 0.5],
					"cubes": [
						{"origin": [-2, 30.5, -1.5], "size": [4, 1, 4], "uv": [0, 65]},
						{"origin": [-3, 29.5, -2], "size": [6, 2, 5], "inflate": -0.02, "uv": [32, 55]},
						{"origin": [-4.5, 19.5, -2.5], "size": [9, 11, 6], "inflate": 0.25, "uv": [38, 0]},
						{"origin": [-4.5, 23.5, -2.5], "size": [9, 7, 6], "uv": [32, 17]}
					]
				},
				{
					"name": "head",
					"parent": "torso",
					"pivot": [0, 31, 1.5],
					"cubes": [
						{"origin": [-2.5, 31.5, -2], "size": [5, 6, 5], "uv": [0, 46]},
						{"origin": [-3, 34.5, -2], "size": [6, 9, 5], "inflate": 0.02, "uv": [21, 41]},
						{"origin": [3, 34.5, 1], "size": [4, 7, 0], "inflate": 0.02, "uv": [56, 62], "mirror": true},
						{"origin": [3, 30.5, 1], "size": [0, 8, 2], "inflate": -0.01, "pivot": [3, 37.5, 2], "rotation": [0, 0, -7.5], "uv": [2, 33]},
						{"origin": [-7, 34.5, 1], "size": [4, 7, 0], "inflate": 0.02, "uv": [56, 62]},
						{"origin": [-3, 30.5, 1], "size": [0, 8, 2], "inflate": -0.01, "pivot": [-3, 37.5, 2], "rotation": [0, 0, 7.5], "uv": [2, 33], "mirror": true},
						{"origin": [-3, 30.5, 3], "size": [6, 8, 0], "inflate": -0.01, "pivot": [-0.5, 37.5, 2.75], "rotation": [15, 0, 0], "uv": [54, 54]}
					]
				},
				{
					"name": "arm",
					"parent": "torso",
					"pivot": [-6.25, 29, 1.25],
					"rotation": [0, 0, 15],
					"cubes": [
						{"origin": [-7.75, 22.25, -1.5], "size": [3, 8, 4], "inflate": 0.4, "uv": [66, 51]}
					]
				},
				{
					"name": "arm4",
					"parent": "arm",
					"pivot": [-2.5, 29.75, 3.5],
					"cubes": [
						{"origin": [-10.5, 27.75, 3.5], "size": [8, 6, 0], "uv": [64, 24], "mirror": true},
						{"origin": [-10.5, 27.75, -3.5], "size": [0, 6, 7], "uv": [42, 55], "mirror": true},
						{"origin": [-10.5, 25.75, -3.5], "size": [5, 8, 0], "uv": [32, 62], "mirror": true}
					]
				},
				{
					"name": "forearm",
					"parent": "arm",
					"pivot": [-7.75, 22, -0.5],
					"rotation": [45, 0, 0],
					"cubes": [
						{"origin": [-7.75, 19.5, -7.5], "size": [3, 3, 8], "inflate": 0.01, "uv": [43, 43]},
						{"origin": [-7.75, 19.5, -11.5], "size": [3, 4, 4], "inflate": -0.01, "uv": [0, 57]},
						{"origin": [-7.75, 19.5, -18.5], "size": [0, 3, 7], "inflate": -0.01, "uv": [30, 24]}
					]
				},
				{
					"name": "arm2",
					"parent": "torso",
					"pivot": [6.75, 28.75, 0.5],
					"rotation": [0, 0, -15],
					"cubes": [
						{"origin": [4.25, 21.75, -1.5], "size": [4, 11, 4], "inflate": 0.6, "uv": [16, 55]},
						{"origin": [5, 22, -1.5], "size": [3, 8, 4], "inflate": 0.4, "uv": [66, 30]}
					]
				},
				{
					"name": "arm3",
					"parent": "arm2",
					"pivot": [3.75, 29.75, 3.5],
					"cubes": [
						{"origin": [3.75, 27.75, 3.5], "size": [8, 6, 0], "uv": [64, 24]},
						{"origin": [11.75, 27.75, -3.5], "size": [0, 6, 7], "uv": [42, 55]},
						{"origin": [6.75, 25.75, -3.5], "size": [5, 8, 0], "uv": [32, 62]}
					]
				},
				{
					"name": "forearm2",
					"parent": "arm2",
					"pivot": [5.75, 22, -0.5],
					"rotation": [45, 0, 0],
					"cubes": [
						{"origin": [5, 19.25, -7.5], "size": [3, 3, 8], "inflate": 0.01, "uv": [0, 35]},
						{"origin": [5, 19.25, -11.5], "size": [3, 4, 4], "inflate": -0.01, "uv": [57, 43]}
					]
				},
				{
					"name": "wing",
					"parent": "torso",
					"pivot": [1, 29.25, 3.75],
					"cubes": [
						{"origin": [1, 25.25, 3.75], "size": [0, 20, 19], "pivot": [1, 29.25, 3.75], "rotation": [-7.5, 60, 7.5], "uv": [0, -19]}
					]
				},
				{
					"name": "wing2",
					"parent": "torso",
					"pivot": [-3, 29.25, 3.75],
					"cubes": [
						{"origin": [-3, 25.25, 3.75], "size": [0, 20, 19], "pivot": [-3, 29.25, 3.75], "rotation": [-7.5, -60, -7.5], "uv": [0, -19], "mirror": true}
					]
				},
				{
					"name": "wing3",
					"parent": "torso",
					"pivot": [-0.5, 28, 3.25],
					"rotation": [-22.5, 0, 37.5],
					"cubes": [
						{"origin": [-0.5, 25, 3.25], "size": [0, 20, 19], "pivot": [-0.5, 28, 3.25], "rotation": [-7.5, 60, 7.5], "uv": [0, -19]}
					]
				},
				{
					"name": "wing4",
					"parent": "torso",
					"pivot": [-1.5, 28, 3.25],
					"rotation": [-22.5, 0, -37.5],
					"cubes": [
						{"origin": [-1.5, 25, 3.25], "size": [0, 20, 19], "pivot": [-1.5, 28, 3.25], "rotation": [-7.5, -60, -7.5], "uv": [0, -19], "mirror": true}
					]
				},
				{
					"name": "body3",
					"parent": "body",
					"pivot": [-4, 21.25, 3.5],
					"rotation": [7.5, 15, 7.5],
					"cubes": [
						{"origin": [-4, 15.25, -3.5], "size": [5, 8, 0], "uv": [32, 62], "mirror": true},
						{"origin": [-4, 17.25, -3.5], "size": [0, 6, 7], "uv": [42, 55], "mirror": true}
					]
				},
				{
					"name": "body2",
					"parent": "body",
					"pivot": [4, 21.25, 3.5],
					"rotation": [7.5, -15, -7.5],
					"cubes": [
						{"origin": [-1, 15.25, -3.5], "size": [5, 8, 0], "uv": [32, 62]},
						{"origin": [4, 17.25, -3.5], "size": [0, 6, 7], "uv": [42, 55]}
					]
				},
				{
					"name": "leg",
					"parent": "entity",
					"pivot": [2.5, 17, 0.5],
					"rotation": [0, 0, -7.5],
					"cubes": [
						{"origin": [1, 10.75, -1.5], "size": [3, 6, 4], "inflate": -0.01, "uv": [64, 14]}
					]
				},
				{
					"name": "leg4",
					"parent": "leg",
					"pivot": [2.5, 10.75, 1.5],
					"rotation": [0, 0, 7.5],
					"cubes": [
						{"origin": [0, 2.75, -2.5], "size": [5, 9, 6], "inflate": -0.01, "uv": [0, 20]},
						{"origin": [0.5, 0, -4.5], "size": [4, 3, 8], "inflate": -0.1, "uv": [14, 27]}
					]
				},
				{
					"name": "leg2",
					"parent": "entity",
					"pivot": [-2.5, 17, 0.5],
					"rotation": [0, 0, 7.5],
					"cubes": [
						{"origin": [-4, 10.75, -1.5], "size": [3, 6, 4], "inflate": -0.01, "uv": [64, 14], "mirror": true}
					]
				},
				{
					"name": "leg3",
					"parent": "leg2",
					"pivot": [-2.5, 10.75, 1.5],
					"rotation": [0, 0, -7.5],
					"cubes": [
						{"origin": [-5, 2.75, -2.5], "size": [5, 9, 6], "inflate": -0.01, "uv": [0, 20], "mirror": true},
						{"origin": [-4.5, 0, -4.5], "size": [4, 3, 8], "inflate": -0.1, "uv": [14, 27], "mirror": true}
					]
				}
			]
		}
	]
}